{"miller": "210_0.32", "final_energy": -1204.29666477, "gamma": 0.016665312793660198, "work_function": "Not calculated", "ionization_potentail": "Not calculated", "electron_affinity": "Not calculated", "is_stochiometric": false, "incar_parameters": {"SYSTEM": "unknown system", "LCOMPAT": false, "PREC": "normal", "ENMAX": 520.0, "ENAUG": 628.945, "EDIFF": 1e-05, "IALGO": 38, "IWAVPR": 11, "NBANDS": 1039, "NBANDSLOW": -1, "NBANDSHIGH": -1, "NELECT": 1732.0, "TURBO": 0, "IRESTART": 0, "NREBOOT": 0, "NMIN": 0, "EREF": 0.0, "ISMEAR": 0, "SIGMA": 0.05, "KSPACING": 0.5, "KGAMMA": true, "KBLOWUP": true, "LREAL": true, "ROPT": [-0.0005, -0.0005, -0.0005], "LMAXPAW": -100, "LMAXMIX": 4, "NLSPLINE": false, "ISTART": 0, "ICHARG": 2, "INIWAV": 1, "ISPIN": 1, "LNONCOLLINEAR": false, "MAGMOM": [0.6, 0.6, 0.6, 0.6, 0.6, 0.6, 0.6, 0.6, 0.6, 0.6, 0.6, 0.6, 0.6, 0.6, 0.6, 0.6, 0.6, 0.6, 0.6, 0.6, 0.6, 0.6, 0.6, 0.6, 0.6, 0.6, 0.6, 0.6, 0.6, 0.6, 0.6, 0.6, 0.6, 0.6, 0.6, 0.6, 0.6, 0.6, 0.6, 0.6, 0.6, 0.6, 0.6, 0.6, 0.6, 0.6, 0.6, 0.6, 0.6, 0.6, 0.6, 0.6, 0.6, 0.6, 0.6, 0.6, 0.6, 0.6, 0.6, 0.6, 0.6, 0.6, 0.6, 0.6, 0.6, 0.6, 0.6, 0.6, 0.6, 0.6, 0.6, 0.6, 0.6, 0.6, 0.6, 0.6, 0.6, 0.6, 0.6, 0.6, 0.6, 0.6, 0.6, 0.6, 0.6, 0.6, 0.6, 0.6, 0.6, 0.6, 0.6, 0.6, 0.6, 0.6, 0.6, 0.6, 0.6, 0.6, 0.6, 0.6, 0.6, 0.6, 0.6, 0.6, 0.6, 0.6, 0.6, 0.6, 0.6, 0.6, 0.6, 0.6, 0.6, 0.6, 0.6, 0.6, 0.6, 0.6, 0.6, 0.6, 0.6, 0.6, 0.6, 0.6, 0.6, 0.6, 0.6, 0.6, 0.6, 0.6, 0.6, 0.6, 0.6, 0.6, 0.6, 0.6, 0.6, 0.6, 0.6, 0.6, 0.6, 0.6, 0.6, 0.6, 0.6, 0.6, 0.6, 0.6, 0.6, 0.6, 0.6, 0.6, 0.6, 0.6, 0.6, 0.6, 0.6, 0.6, 0.6, 0.6, 0.6, 0.6, 0.6, 0.6, 0.6, 0.6, 0.6, 0.6, 0.6, 0.6, 0.6, 0.6, 0.6, 0.6, 0.6, 0.6, 0.6, 0.6, 0.6, 0.6, 0.6, 0.6, 0.6, 0.6, 0.6, 0.6, 0.6, 0.6, 0.6, 0.6, 0.6, 0.6, 0.6, 0.6, 0.6, 0.6, 0.6, 0.6, 0.6, 0.6, 0.6, 0.6, 0.6, 0.6, 0.6, 0.6, 0.6, 0.6, 0.6, 0.6, 0.6, 0.6, 0.6, 0.6, 0.6, 0.6, 0.6, 0.6, 0.6, 0.6, 0.6, 0.6, 0.6, 0.6, 0.6, 0.6, 0.6, 0.6, 0.6, 0.6, 0.6, 0.6, 0.6, 0.6, 0.6, 0.6, 0.6, 0.6, 0.6, 0.6, 0.6, 0.6, 0.6, 0.6, 0.6, 0.6, 0.6, 0.6, 0.6, 0.6, 0.6, 0.6, 0.6, 0.6, 0.6, 0.6, 0.6, 0.6, 0.6, 0.6, 0.6, 0.6, 0.6, 0.6, 0.6, 0.6, 0.6, 0.6, 0.6, 0.6, 0.6, 0.6, 0.6, 0.6, 0.6, 0.6, 0.6, 0.6, 0.6, 0.6, 0.6, 0.6, 0.6, 0.6], "NUPDOWN": -1.0, "LSORBIT": false, "SAXIS": [0.0, 0.0, 1.0], "LSPIRAL": false, "QSPIRAL": [0.0, 0.0, 0.0], "LZEROZ": false, "LASPH": false, "LMETAGGA": false, "NELM": 100, "NELMDL": -5, "NELMIN": 6, "ENINI": 520.0, "LDIAG": true, "LSUBROT": false, "WEIMIN": 0.001, "EBREAK": 0.0, "DEPER": 0.3, "NRMM": 4, "TIME": 0.4, "AMIX": 0.4, "BMIX": 1.0, "AMIN": 0.1, "AMIX_MAG": 1.6, "BMIX_MAG": 1.0, "IMIX": 4, "MIXFIRST": false, "MAXMIX": -45, "WC": 100.0, "INIMIX": 1, "MIXPRE": 1, "MREMOVE": 5, "LDIPOL": false, "LMONO": false, "IDIPOL": 0, "EPSILON": 1.0, "DIPOL": [-100.0, -100.0, -100.0], "EFIELD": 0.0, "NGX": 64, "NGY": 140, "NGZ": 270, "NGXF": 128, "NGYF": 280, "NGZF": 540, "ADDGRID": false, "NSW": 150, "IBRION": 2, "MDALGO": 0, "ISIF": 2, "PSTRESS": 0.0, "EDIFFG": -0.01, "NFREE": 1, "POTIM": 0.5, "SMASS": -3.0, "SCALEE": 1.0, "TEBEG": 0.0001, "TEEND": 0.0001, "NBLOCK": 1, "KBLOCK": 150, "NPACO": 256, "APACO": 10.0, "ISYM": 0, "SYMPREC": 1e-05, "LORBIT": 11, "RWIGS": [-1.0, -1.0, -1.0], "NEDOS": 301, "EMIN": 10.0, "EMAX": -10.0, "EFERMI": 0.0, "NWRITE": 2, "LWAVE": false, "LDOWNSAMPLE": false, "LCHARG": false, "LPARD": false, "LVTOT": false, "LVHAR": false, "LELF": false, "LOPTICS": false, "STM": [0.0, 0.0, 0.0, 0.0, 0.0, 0.0, 0.0], "NPAR": 1, "NSIM": 4, "NBLK": -1, "LPLANE": true, "LSCALAPACK": true, "LSCAAWARE": false, "LSCALU": false, "LASYNC": false, "LORBITALREAL": false, "IDIOT": 3, "PHON_NSTRUCT": -1, "LMUSIC": false, "POMASS": [7.01, 88.906, 35.453], "DARWINR": [0.0, 0.0, 0.0], "DARWINV": [1.0, 1.0, 1.0], "LCORR": true, "GGA_COMPAT": true, "LBERRY": false, "ICORELEVEL": 0, "LDAU": false, "I_CONSTRAINED_M": 0, "GGA": "--", "VOSKOWN": 0, "LHFCALC": false, "PRECFOCK": "", "LSYMGRAD": false, "LHFONE": false, "LRHFCALC": false, "LTHOMAS": false, "LMODELHF": false, "LFOCKACE": false, "ENCUT4O": -1.0, "EXXOEP": 0, "FOURORBIT": 0, "AEXX": 0.0, "HFALPHA": 0.0, "MCALPHA": 0.0, "ALDAX": 1.0, "AGGAX": 1.0, "ALDAC": 1.0, "AGGAC": 1.0, "NKREDX": 1, "NKREDY": 1, "NKREDZ": 1, "SHIFTRED": false, "ODDONLY": false, "EVENONLY": false, "LMAXFOCK": 0, "NMAXFOCKAE": 0, "LFOCKAEDFT": false, "HFSCREEN": 0.0, "HFSCREENC": 0.0, "NBANDSGWLOW": 0, "LUSE_VDW": false, "Zab_VDW": -0.8491, "PARAM1": 0.1234, "PARAM2": 1.0, "PARAM3": 0.0, "MODEL_GW": 0, "MODEL_EPS0": 22.3004258, "MODEL_ALPHA": 1.0, "LEPSILON": false, "LRPA": false, "LNABLA": false, "LVEL": false, "CSHIFT": 0.1, "OMEGAMAX": -1.0, "DEG_THRESHOLD": 0.002, "RTIME": -0.1, "WPLASMAI": 0.0, "DFIELD": [0.0, 0.0, 0.0], "WPLASMA": [0.0, 0.0, 0.0, 0.0, 0.0, 0.0, 0.0, 0.0, 0.0], "NUCIND": false, "MAGPOS": [0.0, 0.0, 0.0], "LNICSALL": true, "ORBITALMAG": false, "LMAGBLOCH": false, "LCHIMAG": false, "LGAUGE": true, "MAGATOM": 0, "MAGDIPOL": [0.0, 0.0, 0.0], "AVECCONST": [0.0, 0.0, 0.0], "LFINITE_TEMPERATURE": false, "LADDER": false, "LRPAFORCE": false, "LFXC": false, "LHARTREE": true, "IBSE": 0, "KPOINT": [-1, 0, 0, 0], "LTCTC": false, "LTCTE": false, "LTETE": false, "LTRIPLET": false, "LFXCEPS": false, "LFXHEG": false, "NATURALO": 2, "LHOLEGF": false, "L2ORDER": false, "LDMP1": false, "LMP2LT": false, "LSMP2LT": false, "LGWLF": false, "ENCUTGW": -2.0, "ENCUTGWSOFT": -2.0, "ENCUTLF": -1.0, "LESF_SPLINES": false, "LMAXMP2": -1, "SCISSOR": 0.0, "NOMEGA": 0, "NOMEGAR": 0, "NBANDSGW": -1, "NBANDSO": -1, "NBANDSV": -1, "NELMGW": 1, "NELMHF": 1, "DIM": 3, "IESPILON": 4, "ANTIRES": 0, "OMEGAMIN": -30.0, "OMEGATL": -200.0, "OMEGAGRID": 0, "LSELFENERGY": false, "LSPECTRAL": false, "LSPECTRALGW": false, "LSINGLES": false, "LFERMIGW": false, "ODDONLYGW": false, "EVENONLYGW": false, "NKREDLFX": 1, "NKREDLFY": 1, "NKREDLFZ": 1, "MAXMEM": 2800, "TELESCOPE": 0, "NTAUPAR": -1, "NOMEGAPAR": -1, "DAMP_NEWTON": 0.80000001, "LAMBDA": 1.0, "OFIELD_KAPPA": 0.0, "OFIELD_K": [0.0, 0.0, 0.0], "OFIELD_Q6_NEAR": 0.0, "OFIELD_Q6_FAR": 0.0, "OFIELD_A": 0.0, "KPOINTS_OPT_MODE": 1, "LKPOINTS_OPT": false, "@module": "pymatgen.io.vasp.inputs", "@class": "Incar"}, "relaxed_structures": {"@module": "pymatgen.core.structure", "@class": "Structure", "charge": 0, "lattice": {"matrix": [[11.177228, 0.0, 0.0], [11.177345, 20.297021, 0.0], [0.0, 0.0, 46.527941]], "a": 11.177228, "b": 23.171148066581985, "c": 46.527941, "alpha": 90.0, "beta": 90.0, "gamma": 61.15890919136826, "volume": 10555.534880935946}, "sites": [{"species": [{"element": "Li", "occu": 1}], "abc": [0.73281866, 0.93442582, 0.08621059999999996], "xyz": [18.635281012522377, 18.96606049148222, 4.011201710374598], "label": "Li", "properties": {}}, {"species": [{"element": "Li", "occu": 1}], "abc": [0.7085255, 0.45150404, 0.04414119999999996], "xyz": [12.9659674812878, 9.164186981464841, 2.053799149269198], "label": "Li", "properties": {}}, {"species": [{"element": "Li", "occu": 1}], "abc": [0.41252457, 0.92927165, 0.08947052999999996], "xyz": [14.99767100526121, 18.861446194754652, 4.162879541078728], "label": "Li", "properties": {}}, {"species": [{"element": "Li", "occu": 1}], "abc": [0.30021356, 0.48983104, 0.02929849999999996], "xyz": [8.83056593460048, 9.942110905331841, 1.3631988793884982], "label": "Li", "properties": {}}, {"species": [{"element": "Li", "occu": 1}], "abc": [0.73625982, 0.09086765, 0.10929241999999996], "xyz": [9.24500294876821, 1.84434260027065, 5.085151269507218], "label": "Li", "properties": {}}, {"species": [{"element": "Li", "occu": 1}], "abc": [0.66080034, 0.62411041, 0.03664140999999996], "xyz": [14.36181343331897, 12.66758209808861, 1.704849362636808], "label": "Li", "properties": {}}, {"species": [{"element": "Li", "occu": 1}], "abc": [0.05699871, 0.12142389, 0.05922426999999996], "xyz": [1.99428428714793, 2.4645432452316904, 2.755583340328068], "label": "Li", "properties": {}}, {"species": [{"element": "Li", "occu": 1}], "abc": [0.1074571, 0.58819513, 0.10682417999999996], "xyz": [7.7755324022486505, 11.938608905707731, 4.9703091444133785], "label": "Li", "properties": {}}, {"species": [{"element": "Li", "occu": 1}], "abc": [0.02497629, 0.25931471, 0.056720279999999956], "xyz": [3.1776156651690703, 5.2633161144789105, 2.639077841343478], "label": "Li", "properties": {}}, {"species": [{"element": "Li", "occu": 1}], "abc": [0.99779746, 0.82779737, 0.01239471999999996], "xyz": [20.40518650282353, 16.80182060263477, 0.5767008008715181], "label": "Li", "properties": {}}, {"species": [{"element": "Li", "occu": 1}], "abc": [0.70243747, 0.13938071, 0.04905208999999996], "xyz": [9.40921003994811, 2.82901319786491, 2.282292749446688], "label": "Li", "properties": {}}, {"species": [{"element": "Li", "occu": 1}], "abc": [0.92359813, 0.53339608, 0.08173047999999997], "xyz": [16.285218887191242, 10.826351437077681, 3.8027509513416784], "label": "Li", "properties": {}}, {"species": [{"element": "Li", "occu": 1}], "abc": [0.37605128, 0.96638206, 0.03261933999999996], "xyz": [15.004796582682541, 19.614676965843262, 1.5177107269789383], "label": "Li", "properties": {}}, {"species": [{"element": "Li", "occu": 1}], "abc": [0.28131684, 0.40179477, 0.07162502999999996], "xyz": [7.63534122440517, 8.155236884380171, 3.332565169963228], "label": "Li", "properties": {}}, {"species": [{"element": "Li", "occu": 1}], "abc": [0.61487312, 0.30757863, 0.03913026999999996], "xyz": [10.310489515448712, 6.24292991226123, 1.820650893874068], "label": "Li", "properties": {}}, {"species": [{"element": "Li", "occu": 1}], "abc": [0.38970538, 0.77267947, 0.05708159999999996], "xyz": [12.99233089569379, 15.683091428858871, 2.655889316985598], "label": "Li", "properties": {}}, {"species": [{"element": "Li", "occu": 1}], "abc": [0.86992181, 0.23894142, 0.00736268999999996], "xyz": [12.39404509867258, 4.84979901950982, 0.34257080592128814], "label": "Li", "properties": {}}, {"species": [{"element": "Li", "occu": 1}], "abc": [0.05398293, 0.77557328, 0.06628610999999995], "xyz": [9.27222964005964, 15.741827151198882, 3.0841562151995077], "label": "Li", "properties": {}}, {"species": [{"element": "Li", "occu": 1}], "abc": [0.82120449, 0.84845812, 0.21238577999999994], "xyz": [18.66229894464512, 17.22117227926052, 9.881873041078977], "label": "Li", "properties": {}}, {"species": [{"element": "Li", "occu": 1}], "abc": [0.76946132, 0.39546589, 0.14787320999999995], "xyz": [13.02070329908301, 8.02677947411369, 6.880235990360608], "label": "Li", "properties": {}}, {"species": [{"element": "Li", "occu": 1}], "abc": [0.49350007, 0.84620737, 0.21364993999999995], "xyz": [14.97431451643861, 17.17548875924477, 9.940691802973538], "label": "Li", "properties": {}}, {"species": [{"element": "Li", "occu": 1}], "abc": [0.43179861, 0.4040606, 0.14597967999999995], "xyz": [9.34263624116008, 8.2012264834726, 6.7921339382388775], "label": "Li", "properties": {}}, {"species": [{"element": "Li", "occu": 1}], "abc": [0.8359136, 0.99875252, 0.23440799999999995], "xyz": [20.506598381160202, 20.27170087224292, 10.906521593927998], "label": "Li", "properties": {}}, {"species": [{"element": "Li", "occu": 1}], "abc": [0.7859464, 0.54489799, 0.16619686999999994], "xyz": [14.875214932615751, 11.059805945887792, 7.732798161744667], "label": "Li", "properties": {}}, {"species": [{"element": "Li", "occu": 1}], "abc": [0.12479763, 0.04527137, 0.17589117999999995], "xyz": [1.90090528548229, 0.9188739475887701, 8.183854445460378], "label": "Li", "properties": {}}, {"species": [{"element": "Li", "occu": 1}], "abc": [0.1678849, 0.49945452, 0.23432615999999995], "xyz": [7.4590632869066, 10.13743888098492, 10.902713747236557], "label": "Li", "properties": {}}, {"species": [{"element": "Li", "occu": 1}], "abc": [0.12274609, 0.2044628, 0.19332440999999995], "xyz": [3.65731228930452, 4.1499857453188005, 8.994986742339806], "label": "Li", "properties": {}}, {"species": [{"element": "Li", "occu": 1}], "abc": [0.0891968, 0.74023741, 0.12927507999999996], "xyz": [9.27086188394685, 15.02461425575561, 6.014903295010278], "label": "Li", "properties": {}}, {"species": [{"element": "Li", "occu": 1}], "abc": [0.7904629, 0.04128483, 0.17183654999999995], "xyz": [9.29663884701755, 0.8379590614914301, 7.995200860043547], "label": "Li", "properties": {}}, {"species": [{"element": "Li", "occu": 1}], "abc": [0.83094264, 0.49538916, 0.23208898999999994], "xyz": [14.82477089278212, 10.05492418369236, 10.798622833469587], "label": "Li", "properties": {}}, {"species": [{"element": "Li", "occu": 1}], "abc": [0.46072461, 0.89329789, 0.15180856999999995], "xyz": [15.13432271548313, 18.13128603258569, 7.063340188254367], "label": "Li", "properties": {}}, {"species": [{"element": "Li", "occu": 1}], "abc": [0.492361, 0.35137429, 0.21234114999999995], "xyz": [9.430662818768049, 7.13185134299009, 9.879796499072148], "label": "Li", "properties": {}}, {"species": [{"element": "Li", "occu": 1}], "abc": [0.46277817, 0.20078668, 0.19415311999999996], "xyz": [7.4168391132773595, 4.07537146048028, 9.033544912325917], "label": "Li", "properties": {}}, {"species": [{"element": "Li", "occu": 1}], "abc": [0.44555697, 0.73142848, 0.13889245999999994], "xyz": [13.15552030446476, 14.845819218558082, 6.462380184224857], "label": "Li", "properties": {}}, {"species": [{"element": "Li", "occu": 1}], "abc": [0.08992286, 0.24245143, 0.12731653999999995], "xyz": [3.71505158748543, 4.92104176619003, 5.923776461444137], "label": "Li", "properties": {}}, {"species": [{"element": "Li", "occu": 1}], "abc": [0.13635522, 0.69765315, 0.19231549999999994], "xyz": [9.321983330816911, 14.160280636266151, 8.948044237385497], "label": "Li", "properties": {}}, {"species": [{"element": "Li", "occu": 1}], "abc": [0.90967461, 0.75759949, 0.33881641999999995], "xyz": [18.63559139333513, 15.377012758119292, 15.764430399591218], "label": "Li", "properties": {}}, {"species": [{"element": "Li", "occu": 1}], "abc": [0.86423014, 0.3041532, 0.2757549799999999], "xyz": [13.05932256850592, 6.173403887617201, 12.830311439896176], "label": "Li", "properties": {}}, {"species": [{"element": "Li", "occu": 1}], "abc": [0.58130307, 0.75620425, 0.33879982999999997], "xyz": [14.949712743206211, 15.348693542539252, 15.763658501050028], "label": "Li", "properties": {}}, {"species": [{"element": "Li", "occu": 1}], "abc": [0.53236915, 0.30518733, 0.2760153699999999], "xyz": [9.361595446755048, 6.19439364594393, 12.842426850453165], "label": "Li", "properties": {}}, {"species": [{"element": "Li", "occu": 1}], "abc": [0.92632662, 0.90944191, 0.35903200999999996], "xyz": [20.51890981973831, 18.45896154555011, 16.705020178391408], "label": "Li", "properties": {}}, {"species": [{"element": "Li", "occu": 1}], "abc": [0.87867289, 0.45381546, 0.29657502999999996], "xyz": [14.89357919170262, 9.21110192174466, 13.799025497913227], "label": "Li", "properties": {}}, {"species": [{"element": "Li", "occu": 1}], "abc": [0.21558571, 0.95383237, 0.29909192999999995], "xyz": [13.070964105869532, 19.35995564436977, 13.916131672616126], "label": "Li", "properties": {}}, {"species": [{"element": "Li", "occu": 1}], "abc": [0.25948537, 0.41108883, 0.3621459799999999], "xyz": [7.49520882171071, 8.34387861537543, 16.849906790827177], "label": "Li", "properties": {}}, {"species": [{"element": "Li", "occu": 1}], "abc": [0.21563729, 0.11369332, 0.31909219999999994], "xyz": [3.6810166174675203, 2.30763570359972, 14.846703055160196], "label": "Li", "properties": {}}, {"species": [{"element": "Li", "occu": 1}], "abc": [0.17204001, 0.65549451, 0.25580120999999995], "xyz": [9.249618700768231, 13.304585834854711, 11.901903606608608], "label": "Li", "properties": {}}, {"species": [{"element": "Li", "occu": 1}], "abc": [0.88450935, 0.9478693, 0.29595346999999994], "xyz": [20.4810248540903, 19.2389230873553, 13.770105590905267], "label": "Li", "properties": {}}, {"species": [{"element": "Li", "occu": 1}], "abc": [0.92338163, 0.40444449, 0.3590563399999999], "xyz": [14.84146260760069, 8.20901830686429, 16.706152203195934], "label": "Li", "properties": {}}, {"species": [{"element": "Li", "occu": 1}], "abc": [0.54728523, 0.80209272, 0.27597531999999997], "xyz": [15.08239885017084, 16.280092781787122, 12.840563406416118], "label": "Li", "properties": {}}, {"species": [{"element": "Li", "occu": 1}], "abc": [0.59058075, 0.25936092, 0.3387361099999999], "xyz": [9.5000221775184, 5.2642540398193205, 15.760693740649506], "label": "Li", "properties": {}}, {"species": [{"element": "Li", "occu": 1}], "abc": [0.56045976, 0.10854997, 0.31607498999999994], "xyz": [7.477686986774929, 2.20324102063937, 14.706318486295586], "label": "Li", "properties": {}}, {"species": [{"element": "Li", "occu": 1}], "abc": [0.51874798, 0.65056726, 0.25310741], "xyz": [13.06977915772414, 13.20457733813246, 11.776566639142809], "label": "Li", "properties": {}}, {"species": [{"element": "Li", "occu": 1}], "abc": [0.18317143, 0.15324323, 0.25550628999999997], "xyz": [3.76020128682039, 3.1103810574178303, 11.888181586248889], "label": "Li", "properties": {}}, {"species": [{"element": "Li", "occu": 1}], "abc": [0.22520851, 0.60740185, 0.31828298999999993], "xyz": [9.306346894898532, 12.328448104888851, 14.809052180023587], "label": "Li", "properties": {}}, {"species": [{"element": "Li", "occu": 1}], "abc": [0.99852028, 0.66685464, 0.46657230999999993], "xyz": [18.61435320831464, 13.535162632027442, 21.708648911913706], "label": "Li", "properties": {}}, {"species": [{"element": "Li", "occu": 1}], "abc": [0.95734217, 0.21336439, 0.40276783999999993], "xyz": [13.08527910584931, 4.33066150448219, 18.739958296217438], "label": "Li", "properties": {}}, {"species": [{"element": "Li", "occu": 1}], "abc": [0.67927647, 0.6584785, 0.46870591999999994], "xyz": [14.95246934980766, 13.3651519425485, 21.807921392110718], "label": "Li", "properties": {}}, {"species": [{"element": "Li", "occu": 1}], "abc": [0.62397324, 0.21572452, 0.40135365999999995], "xyz": [9.38551855437812, 4.37856511265492, 18.674159412614056], "label": "Li", "properties": {}}, {"species": [{"element": "Li", "occu": 1}], "abc": [0.01338046, 0.81887813, 0.4873694499999999], "xyz": [9.302439824129731, 16.62078660105073, 22.676297014802447], "label": "Li", "properties": {}}, {"species": [{"element": "Li", "occu": 1}], "abc": [0.96950525, 0.36382147, 0.42284853999999994], "xyz": [14.902939315044149, 7.38449201684087, 19.674271921056135], "label": "Li", "properties": {}}, {"species": [{"element": "Li", "occu": 1}], "abc": [0.30238727, 0.86100621, 0.42011282999999994], "xyz": [13.00361491740001, 17.475861125500412, 19.546984967583025], "label": "Li", "properties": {}}, {"species": [{"element": "Li", "occu": 1}], "abc": [0.34644796, 0.33034927, 0.47696384999999997], "xyz": [7.564755600343029, 6.7051060705246694, 22.192145871932848], "label": "Li", "properties": {}}, {"species": [{"element": "Li", "occu": 1}], "abc": [0.31211544, 0.02044399, 0.4430968699999999], "xyz": [3.7170949646068703, 0.41495209435379, 20.616385024644664], "label": "Li", "properties": {}}, {"species": [{"element": "Li", "occu": 1}], "abc": [0.25989359, 0.56685842, 0.38291142999999994], "xyz": [9.240862037663419, 11.50553725476682, 17.81608042326563], "label": "Li", "properties": {}}, {"species": [{"element": "Li", "occu": 1}], "abc": [0.96936907, 0.8568072, 0.42117206999999995], "xyz": [20.411688784421962, 17.3906337313512, 19.596269223807866], "label": "Li", "properties": {}}, {"species": [{"element": "Li", "occu": 1}], "abc": [0.00602578, 0.32104507, 0.48605160999999997], "xyz": [3.6557830248769903, 6.51625852773647, 22.614980633035007], "label": "Li", "properties": {}}, {"species": [{"element": "Li", "occu": 1}], "abc": [0.63475931, 0.71049074, 0.4026111399999999], "xyz": [15.03624965327798, 14.42084547008554, 18.732667367862735], "label": "Li", "properties": {}}, {"species": [{"element": "Li", "occu": 1}], "abc": [0.68428411, 0.16832791, 0.46275201999999993], "xyz": [9.52985863744603, 3.41655512415611, 21.530898684190817], "label": "Li", "properties": {}}, {"species": [{"element": "Li", "occu": 1}], "abc": [0.65418252, 0.01592975, 0.4387787799999999], "xyz": [7.48999949116831, 0.32332647027475, 20.415473187891976], "label": "Li", "properties": {}}, {"species": [{"element": "Li", "occu": 1}], "abc": [0.60544069, 0.56152885, 0.38113164999999993], "xyz": [13.04355031651057, 11.39736286055585, 17.733270924432645], "label": "Li", "properties": {}}, {"species": [{"element": "Li", "occu": 1}], "abc": [0.27311376, 0.06294581, 0.38080671999999993], "xyz": [3.75622180013173, 1.2776124274320102, 17.718152600563517], "label": "Li", "properties": {}}, {"species": [{"element": "Li", "occu": 1}], "abc": [0.3144924, 0.51705927, 0.44904089999999997], "xyz": [9.294503105305349, 10.494762861434669, 20.892948501786897], "label": "Li", "properties": {}}, {"species": [{"element": "Li", "occu": 1}], "abc": [0.05130404, 0.61018626, 0.57007888], "xyz": [7.39369929468082, 12.38496333313146, 26.524596493986078], "label": "Li", "properties": {}}, {"species": [{"element": "Li", "occu": 1}], "abc": [0.04228045, 0.1258879, 0.5292536299999999], "xyz": [1.8796707192181001, 2.5551493499459, 24.625081670675826], "label": "Li", "properties": {}}, {"species": [{"element": "Li", "occu": 1}], "abc": [0.72293322, 0.57077683, 0.58532902], "xyz": [14.46015897563051, 11.585069304823431, 27.23415410814782], "label": "Li", "properties": {}}, {"species": [{"element": "Li", "occu": 1}], "abc": [0.71033144, 0.13207398, 0.5253321099999999], "xyz": [9.41577290043142, 2.68070834561358, 24.442621419485505], "label": "Li", "properties": {}}, {"species": [{"element": "Li", "occu": 1}], "abc": [0.78632017, 0.82277075, 0.60723191], "xyz": [17.98527234974751, 16.69979519093575, 28.25325048179731], "label": "Li", "properties": {}}, {"species": [{"element": "Li", "occu": 1}], "abc": [0.04545489, 0.28367442, 0.5486502499999999], "xyz": [3.6787865292598196, 5.75774565990282, 25.527566461635246], "label": "Li", "properties": {}}, {"species": [{"element": "Li", "occu": 1}], "abc": [0.67016763, 0.75431493, 0.57503463], "xyz": [15.92185460999049, 15.310345974823532, 26.75517733759683], "label": "Li", "properties": {}}, {"species": [{"element": "Li", "occu": 1}], "abc": [0.37579972, 0.28775253, 0.55748396], "xyz": [7.41670845520901, 5.840519144213131, 25.93858079932636], "label": "Li", "properties": {}}, {"species": [{"element": "Li", "occu": 1}], "abc": [0.42032287, 0.92209138, 0.56566485], "xyz": [15.00457802739046, 18.71570810377898, 26.31922076657385], "label": "Li", "properties": {}}, {"species": [{"element": "Li", "occu": 1}], "abc": [0.43202764, 0.52768578, 0.5330228199999999], "xyz": [10.72699744923602, 10.71044935806138, 24.800454320613614], "label": "Li", "properties": {}}, {"species": [{"element": "Li", "occu": 1}], "abc": [0.98459356, 0.80223267, 0.5583446599999999], "xyz": [19.97185803031283, 16.28293334987607, 25.978627398145058], "label": "Li", "properties": {}}, {"species": [{"element": "Li", "occu": 1}], "abc": [0.09422369, 0.23283332, 0.6029645499999999], "xyz": [3.65561801126672, 4.72582278553972, 28.054699007491546], "label": "Li", "properties": {}}, {"species": [{"element": "Li", "occu": 1}], "abc": [0.52218285, 0.66018323, 0.5434563499999999], "xyz": [13.215652497064148, 13.39975288315783, 25.285904988875345], "label": "Li", "properties": {}}, {"species": [{"element": "Li", "occu": 1}], "abc": [0.74830954, 0.09465329, 0.58243072], "xyz": [9.421998820870169, 1.9211798148490902, 27.099302176747518], "label": "Li", "properties": {}}, {"species": [{"element": "Li", "occu": 1}], "abc": [0.74032247, 0.93941322, 0.55530419], "xyz": [18.77489869821406, 19.067289854017623, 25.83716058937279], "label": "Li", "properties": {}}, {"species": [{"element": "Li", "occu": 1}], "abc": [0.72259065, 0.47454353, 0.50724288], "xyz": [13.38069719804605, 9.63181999382413, 23.60096679331008], "label": "Li", "properties": {}}, {"species": [{"element": "Li", "occu": 1}], "abc": [0.35660031, 0.97080579, 0.5053904699999999], "xyz": [14.836834212568231, 19.704465506551593, 23.514777970122267], "label": "Li", "properties": {}}, {"species": [{"element": "Li", "occu": 1}], "abc": [0.34833011, 0.43785439, 0.5775158699999999], "xyz": [8.787414635529629, 8.88713974877219, 26.870624325923664], "label": "Li", "properties": {}}, {"species": [{"element": "Y", "occu": 1}], "abc": [0.72916224, 0.77178463, 0.06453726999999995], "xyz": [16.77651568067807, 15.66492884258723, 3.0027862908610676], "label": "Y", "properties": {}}, {"species": [{"element": "Y", "occu": 1}], "abc": [0.40495087, 0.09359828, 0.10835280999999997], "xyz": [5.57240846975496, 1.8997662547238803, 5.041433150864208], "label": "Y", "properties": {}}, {"species": [{"element": "Y", "occu": 1}], "abc": [0.35021407, 0.62554093, 0.03744174999999996], "xyz": [10.90630929542881, 12.69661739256953, 1.7420875349367482], "label": "Y", "properties": {}}, {"species": [{"element": "Y", "occu": 1}], "abc": [0.07014551, 0.93774725, 0.08549701999999997], "xyz": [11.265556894497532, 19.033475625942252, 3.9780003022358184], "label": "Y", "properties": {}}, {"species": [{"element": "Y", "occu": 1}], "abc": [0.75340463, 0.23696832, 0.13258257999999995], "xyz": [11.069651992476041, 4.80975096737472, 6.168794459867778], "label": "Y", "properties": {}}, {"species": [{"element": "Y", "occu": 1}], "abc": [0.80939415, 0.69152805, 0.19205277999999995], "xyz": [16.77623054844345, 14.035959352939049, 8.935820416725978], "label": "Y", "properties": {}}, {"species": [{"element": "Y", "occu": 1}], "abc": [0.49510177, 0.00356823, 0.23482238999999994], "xyz": [5.5737487042429095, 0.07242443924283, 10.925802307398987], "label": "Y", "properties": {}}, {"species": [{"element": "Y", "occu": 1}], "abc": [0.45037828, 0.54722098, 0.17235735999999996], "xyz": [11.15045840650594, 11.10695572270058, 8.019433076995758], "label": "Y", "properties": {}}, {"species": [{"element": "Y", "occu": 1}], "abc": [0.1634162, 0.84782623, 0.21305645999999995], "xyz": [11.302986399052951, 17.20834679466083, 9.913078400548857], "label": "Y", "properties": {}}, {"species": [{"element": "Y", "occu": 1}], "abc": [0.11226832, 0.39068986, 0.15277801999999996], "xyz": [5.62172396303866, 7.92984029290706, 7.108446700656818], "label": "Y", "properties": {}}, {"species": [{"element": "Y", "occu": 1}], "abc": [0.84959014, 0.14789529, 0.25512367999999996], "xyz": [11.149139381536969, 3.0018338069310904, 11.870379530742879], "label": "Y", "properties": {}}, {"species": [{"element": "Y", "occu": 1}], "abc": [0.89443356, 0.60214052, 0.31728349999999994], "xyz": [16.727620161491078, 12.22165877939092, 14.762547968273497], "label": "Y", "properties": {}}, {"species": [{"element": "Y", "occu": 1}], "abc": [0.58335725, 0.91377273, 0.35959237999999993], "xyz": [16.73387004350485, 18.54686429003733, 16.731093040689576], "label": "Y", "properties": {}}, {"species": [{"element": "Y", "occu": 1}], "abc": [0.53761959, 0.45923327, 0.29774666999999994], "xyz": [11.14210542896467, 9.321067325088672, 13.853539494706467], "label": "Y", "properties": {}}, {"species": [{"element": "Y", "occu": 1}], "abc": [0.25230699, 0.75719792, 0.3380594599999999], "xyz": [11.28355513834612, 15.36886208339632, 15.729210609371856], "label": "Y", "properties": {}}, {"species": [{"element": "Y", "occu": 1}], "abc": [0.20572572, 0.30432806, 0.2767779899999999], "xyz": [5.70102299770486, 6.1769530247092606, 12.877909988818585], "label": "Y", "properties": {}}, {"species": [{"element": "Y", "occu": 1}], "abc": [0.94062408, 0.05824078, 0.38015990999999993], "xyz": [11.164547095579339, 1.18211433471638, 17.688057863045305], "label": "Y", "properties": {}}, {"species": [{"element": "Y", "occu": 1}], "abc": [0.98431231, 0.51400122, 0.44242688999999996], "xyz": [16.74705207843758, 10.43269355636562, 20.585212234733486], "label": "Y", "properties": {}}, {"species": [{"element": "Y", "occu": 1}], "abc": [0.66595127, 0.82462434, 0.48226002999999995], "xyz": [16.66059992525686, 16.73741754609114, 22.438566222498228], "label": "Y", "properties": {}}, {"species": [{"element": "Y", "occu": 1}], "abc": [0.63000236, 0.37019965, 0.42284658999999997], "xyz": [11.17952922518733, 7.51395007024265, 19.674181191571186], "label": "Y", "properties": {}}, {"species": [{"element": "Y", "occu": 1}], "abc": [0.33292097, 0.67106901, 0.46204370999999994], "xyz": [11.22190343124961, 13.62070178841921, 21.497942478301105], "label": "Y", "properties": {}}, {"species": [{"element": "Y", "occu": 1}], "abc": [0.29738838, 0.21386418, 0.4019215099999999], "xyz": [5.71441145081274, 4.34080575260778, 18.700580303910908], "label": "Y", "properties": {}}, {"species": [{"element": "Y", "occu": 1}], "abc": [0.03078949, 0.96785771, 0.5063266099999999], "xyz": [11.16222068531367, 19.64462826488191, 23.558334636810006], "label": "Y", "properties": {}}, {"species": [{"element": "Y", "occu": 1}], "abc": [0.0419221, 0.43482205, 0.5768857799999999], "xyz": [5.32872893639605, 8.825592280113051, 26.841307535578974], "label": "Y", "properties": {}}, {"species": [{"element": "Y", "occu": 1}], "abc": [0.71194358, 0.28920714, 0.5504904399999999], "xyz": [11.19012369703954, 5.87004339392994, 25.613186713384035], "label": "Y", "properties": {}}, {"species": [{"element": "Y", "occu": 1}], "abc": [0.3853942, 0.12335269, 0.52923502], "xyz": [5.686394416085649, 2.50369213933649, 24.62421578569382], "label": "Y", "properties": {}}, {"species": [{"element": "Cl", "occu": 1}], "abc": [0.97501334, 0.36039527, 0.11458315999999996], "xyz": [14.92620867337967, 7.31495036349067, 5.331318508073558], "label": "Cl", "properties": {}}, {"species": [{"element": "Cl", "occu": 1}], "abc": [0.92416074, 0.91046941, 0.04711409999999996], "xyz": [20.50618600714517, 18.47981673462761, 2.192122065068098], "label": "Cl", "properties": {}}, {"species": [{"element": "Cl", "occu": 1}], "abc": [0.63734954, 0.35854627, 0.11449500999999995], "xyz": [11.13139648252827, 7.27742117166167, 5.327217070074408], "label": "Cl", "properties": {}}, {"species": [{"element": "Cl", "occu": 1}], "abc": [0.59496384, 0.90349058, 0.04931739999999996], "xyz": [16.74867240834562, 18.33816727556218, 2.294637077473398], "label": "Cl", "properties": {}}, {"species": [{"element": "Cl", "occu": 1}], "abc": [0.60691143, 0.06589546, 0.07045170999999996], "xyz": [7.5201237192697405, 1.33748153542466, 3.277973006229108], "label": "Cl", "properties": {}}, {"species": [{"element": "Cl", "occu": 1}], "abc": [0.52954061, 0.61102109, 9.999999999998899e-05], "xyz": [12.74838965843513, 12.401907895172892, 0.004652794099999487], "label": "Cl", "properties": {}}, {"species": [{"element": "Cl", "occu": 1}], "abc": [0.25764533, 0.2107324, 0.08697032999999996], "xyz": [5.235189334023239, 4.2772399481804, 4.046550382990528], "label": "Cl", "properties": {}}, {"species": [{"element": "Cl", "occu": 1}], "abc": [0.22236277, 0.75901505, 0.02526333999999996], "xyz": [10.96917245304381, 15.40574440916605, 1.175451192982938], "label": "Cl", "properties": {}}, {"species": [{"element": "Cl", "occu": 1}], "abc": [0.31540728, 0.35768272, 0.11663875999999997], "xyz": [7.5233222433982405, 7.259893679177121, 5.426961343593158], "label": "Cl", "properties": {}}, {"species": [{"element": "Cl", "occu": 1}], "abc": [0.26789953, 0.90593422, 0.04620849999999996], "xyz": [13.12031345214874, 18.387765887958622, 2.149986361698498], "label": "Cl", "properties": {}}, {"species": [{"element": "Cl", "occu": 1}], "abc": [0.63153907, 0.20601111, 0.09130835999999996], "xyz": [9.36151342660091, 4.18141182590331, 4.2483899868867585], "label": "Cl", "properties": {}}, {"species": [{"element": "Cl", "occu": 1}], "abc": [0.58905249, 0.74707646, 0.02682207999999996], "xyz": [14.93430531949642, 15.163426597225662, 1.2479761557372782], "label": "Cl", "properties": {}}, {"species": [{"element": "Cl", "occu": 1}], "abc": [0.95111647, 0.20954994, 0.09310917999999996], "xyz": [12.97305761385446, 4.25323953272874, 4.3321784335983775], "label": "Cl", "properties": {}}, {"species": [{"element": "Cl", "occu": 1}], "abc": [0.90791454, 0.76176792, 0.025360159999999958], "xyz": [18.662510669867522, 15.46161946936632, 1.179956028230558], "label": "Cl", "properties": {}}, {"species": [{"element": "Cl", "occu": 1}], "abc": [0.93812534, 0.05997726, 0.06357526999999996], "xyz": [11.15602734493222, 1.21735970574246, 2.958026411619068], "label": "Cl", "properties": {}}, {"species": [{"element": "Cl", "occu": 1}], "abc": [0.29412459, 0.04770887, 0.06783328999999996], "xyz": [3.82075610238667, 0.96834793627627, 3.156143314955888], "label": "Cl", "properties": {}}, {"species": [{"element": "Cl", "occu": 1}], "abc": [0.21389724, 0.59022306, 0.00426989999999996], "xyz": [8.987904988626422, 11.979769843504261, 0.19866965527589814], "label": "Cl", "properties": {}}, {"species": [{"element": "Cl", "occu": 1}], "abc": [0.18906794, 0.81184022, 0.09960816999999995], "xyz": [11.18747369668622, 16.47793799398462, 4.634563056877968], "label": "Cl", "properties": {}}, {"species": [{"element": "Cl", "occu": 1}], "abc": [0.39148242, 0.37436986, 0.029000899999999958], "xyz": [8.560149349153459, 7.59859291018706, 1.349352164146898], "label": "Cl", "properties": {}}, {"species": [{"element": "Cl", "occu": 1}], "abc": [0.52130146, 0.8114348, 0.10232225999999996], "xyz": [14.896391979758882, 16.469709175730802, 4.7608440762666575], "label": "Cl", "properties": {}}, {"species": [{"element": "Cl", "occu": 1}], "abc": [0.70793331, 0.20771566, 0.01369163999999996], "xyz": [10.23444160838738, 4.21600911304886, 0.6370438181132381], "label": "Cl", "properties": {}}, {"species": [{"element": "Cl", "occu": 1}], "abc": [0.49054869, 0.6609496, 0.07454117999999996], "xyz": [12.87063626004332, 13.415307911141602, 3.468247625110378], "label": "Cl", "properties": {}}, {"species": [{"element": "Cl", "occu": 1}], "abc": [0.08772109, 0.17753254, 0.02072500999999996], "xyz": [2.96482107164482, 3.6033816925633397, 0.9642920425044081], "label": "Cl", "properties": {}}, {"species": [{"element": "Cl", "occu": 1}], "abc": [0.16864316, 0.66555391, 0.08314380999999996], "xyz": [9.32408871812943, 13.50876168790211, 3.8685102861952076], "label": "Cl", "properties": {}}, {"species": [{"element": "Cl", "occu": 1}], "abc": [0.84413107, 0.65342102, 0.08346789999999996], "xyz": [16.73855760206586, 13.262500164781422, 3.883589526593898], "label": "Cl", "properties": {}}, {"species": [{"element": "Cl", "occu": 1}], "abc": [0.21883304, 0.9599281, 0.12262913999999996], "xyz": [13.17539433090762, 19.4836808041901, 5.705681390800738], "label": "Cl", "properties": {}}, {"species": [{"element": "Cl", "occu": 1}], "abc": [0.14313665, 0.51170315, 0.06805273999999996], "xyz": [7.3193536173429505, 10.38604958131615, 3.166353871608338], "label": "Cl", "properties": {}}, {"species": [{"element": "Cl", "occu": 1}], "abc": [0.79812383, 0.33645573, 0.03451027999999996], "xyz": [12.68149379158009, 6.82904901738033, 1.6056922717334783], "label": "Cl", "properties": {}}, {"species": [{"element": "Cl", "occu": 1}], "abc": [0.86243473, 0.8132811, 0.09998700999999996], "xyz": [18.72995304900794, 16.5071835656031, 4.652189702046408], "label": "Cl", "properties": {}}, {"species": [{"element": "Cl", "occu": 1}], "abc": [0.86472587, 0.96918357, 0.12048994999999996], "xyz": [20.49813733671001, 19.67153927314497, 5.606149284692948], "label": "Cl", "properties": {}}, {"species": [{"element": "Cl", "occu": 1}], "abc": [0.82015408, 0.51118035, 0.044977879999999956], "xyz": [14.88068827646099, 10.375438298737349, 2.092728146945078], "label": "Cl", "properties": {}}, {"species": [{"element": "Cl", "occu": 1}], "abc": [0.53690586, 0.96393205, 0.12169919999999997], "xyz": [16.775320291163332, 19.56494906142305, 5.662413197347198], "label": "Cl", "properties": {}}, {"species": [{"element": "Cl", "occu": 1}], "abc": [0.47804292, 0.50295492, 0.05556505999999996], "xyz": [10.96489537091316, 10.20848657329332, 2.585327833341458], "label": "Cl", "properties": {}}, {"species": [{"element": "Cl", "occu": 1}], "abc": [0.06591703, 0.27066747, 0.24041656999999994], "xyz": [3.7621133658599906, 5.49374332260687, 11.186087984382366], "label": "Cl", "properties": {}}, {"species": [{"element": "Cl", "occu": 1}], "abc": [0.02394041, 0.81674774, 0.17590862999999995], "xyz": [9.396658688933782, 16.57754603048254, 8.184666358030828], "label": "Cl", "properties": {}}, {"species": [{"element": "Cl", "occu": 1}], "abc": [0.7240466, 0.27383204, 0.24075760999999996], "xyz": [11.153549113958599, 5.55797466635284, 11.201955873381008], "label": "Cl", "properties": {}}, {"species": [{"element": "Cl", "occu": 1}], "abc": [0.67944014, 0.81944861, 0.17706848999999994], "xyz": [16.75351718087237, 16.632365645590813, 8.238632255679088], "label": "Cl", "properties": {}}, {"species": [{"element": "Cl", "occu": 1}], "abc": [0.70144602, 0.97202075, 0.19838016999999994], "xyz": [18.70483336514131, 19.72912557518575, 9.230220845329967], "label": "Cl", "properties": {}}, {"species": [{"element": "Cl", "occu": 1}], "abc": [0.64904675, 0.5151755, 0.13575602999999994], "xyz": [13.012837806456501, 10.4565279421855, 6.316448554234227], "label": "Cl", "properties": {}}, {"species": [{"element": "Cl", "occu": 1}], "abc": [0.3661592, 0.1273904, 0.21741312999999995], "xyz": [5.516531313185601, 2.5856456239984, 10.115785285265327], "label": "Cl", "properties": {}}, {"species": [{"element": "Cl", "occu": 1}], "abc": [0.32217502, 0.6733959, 0.15406987999999994], "xyz": [11.12780195033006, 13.667930723613901, 7.168554286517077], "label": "Cl", "properties": {}}, {"species": [{"element": "Cl", "occu": 1}], "abc": [0.40271593, 0.2764107, 0.23901344999999993], "xyz": [7.5907855244335405, 5.610313782524701, 11.120803699806446], "label": "Cl", "properties": {}}, {"species": [{"element": "Cl", "occu": 1}], "abc": [0.35903793, 0.82335033, 0.17443469999999994], "xyz": [13.215919498531893, 16.71155893836693, 8.116087429952698], "label": "Cl", "properties": {}}, {"species": [{"element": "Cl", "occu": 1}], "abc": [0.71714898, 0.11615112, 0.21646493999999994], "xyz": [9.31399879980384, 2.35752172181352, 10.071667956888536], "label": "Cl", "properties": {}}, {"species": [{"element": "Cl", "occu": 1}], "abc": [0.67344055, 0.66384789, 0.15402319999999994], "xyz": [14.947255465847451, 13.47413456413569, 7.1663823622311975], "label": "Cl", "properties": {}}, {"species": [{"element": "Cl", "occu": 1}], "abc": [0.04582469, 0.1267572, 0.21664818999999993], "xyz": [1.92900196379332, 2.5727935503012, 10.080194202076786], "label": "Cl", "properties": {}}, {"species": [{"element": "Cl", "occu": 1}], "abc": [0.0027907, 0.67300221, 0.15389998999999996], "xyz": [7.553570177112051, 13.659939989416412, 7.160649654620588], "label": "Cl", "properties": {}}, {"species": [{"element": "Cl", "occu": 1}], "abc": [0.02540468, 0.97264402, 0.19449649999999993], "xyz": [11.155531674353941, 19.74177609946442, 9.049521676706497], "label": "Cl", "properties": {}}, {"species": [{"element": "Cl", "occu": 1}], "abc": [0.98019028, 0.51243995, 0.13262333999999995], "xyz": [16.68352835587659, 10.40100442638895, 6.170690938742937], "label": "Cl", "properties": {}}, {"species": [{"element": "Cl", "occu": 1}], "abc": [0.36955977, 0.96971991, 0.19408759999999994], "xyz": [14.969547796356512, 19.68242537738811, 9.030496401631597], "label": "Cl", "properties": {}}, {"species": [{"element": "Cl", "occu": 1}], "abc": [0.31547337, 0.51904333, 0.13429415999999994], "xyz": [9.32764415377721, 10.535033368919931, 6.248430753124557], "label": "Cl", "properties": {}}, {"species": [{"element": "Cl", "occu": 1}], "abc": [0.22888046, 0.26364881, 0.16869033999999994], "xyz": [5.505142794374331, 5.35128543319501, 7.848814186789937], "label": "Cl", "properties": {}}, {"species": [{"element": "Cl", "occu": 1}], "abc": [0.2739697, 0.72410341, 0.23104101999999996], "xyz": [11.15577543123805, 14.69714211894161, 10.749862947139817], "label": "Cl", "properties": {}}, {"species": [{"element": "Cl", "occu": 1}], "abc": [0.56492154, 0.2668459, 0.17186863999999993], "xyz": [9.29688554082662, 5.416176836063901, 7.9966939416702365], "label": "Cl", "properties": {}}, {"species": [{"element": "Cl", "occu": 1}], "abc": [0.6124974, 0.72747063, 0.23177161999999996], "xyz": [14.97721329808455, 14.76548665399323, 10.783856260834417], "label": "Cl", "properties": {}}, {"species": [{"element": "Cl", "occu": 1}], "abc": [0.55928902, 0.11210395, 0.14602187999999994], "xyz": [7.5043254194493105, 2.27537622733295, 6.794097417349077], "label": "Cl", "properties": {}}, {"species": [{"element": "Cl", "occu": 1}], "abc": [0.60101174, 0.57123921, 0.21045094999999994], "xyz": [13.10258297635417, 11.59445424139341, 9.791849384993947], "label": "Cl", "properties": {}}, {"species": [{"element": "Cl", "occu": 1}], "abc": [0.21376494, 0.11900162, 0.14658683999999994], "xyz": [3.7194216350852196, 2.4153783801740203, 6.820383842896437], "label": "Cl", "properties": {}}, {"species": [{"element": "Cl", "occu": 1}], "abc": [0.25237251, 0.58072795, 0.21132170999999994], "xyz": [9.31182173349503, 11.78704739643695, 9.832364054899108], "label": "Cl", "properties": {}}, {"species": [{"element": "Cl", "occu": 1}], "abc": [0.88223583, 0.10872196, 0.14596451999999996], "xyz": [11.07617387767544, 2.2067319052811603, 6.791428574653318], "label": "Cl", "properties": {}}, {"species": [{"element": "Cl", "occu": 1}], "abc": [0.92667837, 0.5681223, 0.20882482999999993], "xyz": [16.70779437345186, 11.5311902536683, 9.716189369575027], "label": "Cl", "properties": {}}, {"species": [{"element": "Cl", "occu": 1}], "abc": [0.3075198, 0.87438318, 0.25041093], "xyz": [13.2105013841715, 17.747373766506783, 11.651104976795128], "label": "Cl", "properties": {}}, {"species": [{"element": "Cl", "occu": 1}], "abc": [0.25712953, 0.4186762, 0.18976733999999995], "xyz": [7.55368371303184, 8.4978796236002, 8.829483599246938], "label": "Cl", "properties": {}}, {"species": [{"element": "Cl", "occu": 1}], "abc": [0.90635689, 0.26727032, 0.16555455999999993], "xyz": [13.117930183801318, 5.4247912977167205, 7.702912799960957], "label": "Cl", "properties": {}}, {"species": [{"element": "Cl", "occu": 1}], "abc": [0.94788408, 0.72725981, 0.22777473999999995], "xyz": [18.723550280734692, 14.76120763602601, 10.597889664010337], "label": "Cl", "properties": {}}, {"species": [{"element": "Cl", "occu": 1}], "abc": [0.95642618, 0.8804626, 0.24876798999999994], "xyz": [20.531427718826038, 17.8707678819146, 11.574662361408587], "label": "Cl", "properties": {}}, {"species": [{"element": "Cl", "occu": 1}], "abc": [0.90255727, 0.42509103, 0.18745828999999994], "xyz": [14.83947748856291, 8.62808156282163, 8.722048257080887], "label": "Cl", "properties": {}}, {"species": [{"element": "Cl", "occu": 1}], "abc": [0.62249856, 0.87701635, 0.24858171999999995], "xyz": [16.76052264938243, 17.80081927329335, 11.565995601838518], "label": "Cl", "properties": {}}, {"species": [{"element": "Cl", "occu": 1}], "abc": [0.57212413, 0.42023243, 0.18549685999999996], "xyz": [11.09184469560999, 8.529466456591031, 8.630786957765258], "label": "Cl", "properties": {}}, {"species": [{"element": "Cl", "occu": 1}], "abc": [0.15604315, 0.18116727, 0.36618181999999994], "xyz": [3.7690989448863497, 3.67715588370267, 17.037686116232617], "label": "Cl", "properties": {}}, {"species": [{"element": "Cl", "occu": 1}], "abc": [0.10777298, 0.72641531, 0.30232296999999997], "xyz": [9.32399770285139, 14.744066801791512, 14.066465311104768], "label": "Cl", "properties": {}}, {"species": [{"element": "Cl", "occu": 1}], "abc": [0.81494478, 0.18461284, 0.36633614999999997], "xyz": [11.172305017579639, 3.74709069034964, 17.044866773367147], "label": "Cl", "properties": {}}, {"species": [{"element": "Cl", "occu": 1}], "abc": [0.7679587, 0.7293613, 0.3030370499999999], "xyz": [16.735972364232097, 14.8038616226873, 14.099689983214045], "label": "Cl", "properties": {}}, {"species": [{"element": "Cl", "occu": 1}], "abc": [0.79050428, 0.88237061, 0.32393420999999994], "xyz": [18.69820729836629, 17.90949480095281, 15.071991810761608], "label": "Cl", "properties": {}}, {"species": [{"element": "Cl", "occu": 1}], "abc": [0.74440634, 0.42660078, 0.26164554999999995], "xyz": [13.088663482154622, 8.658724990276381, 12.173828713312547], "label": "Cl", "properties": {}}, {"species": [{"element": "Cl", "occu": 1}], "abc": [0.45569006, 0.03855082, 0.34316267999999994], "xyz": [5.52424751312658, 0.78246680310722, 15.966652928441876], "label": "Cl", "properties": {}}, {"species": [{"element": "Cl", "occu": 1}], "abc": [0.40950152, 0.58318436, 0.28055584999999994], "xyz": [11.09554464571076, 11.83690520179156, 13.053686036004846], "label": "Cl", "properties": {}}, {"species": [{"element": "Cl", "occu": 1}], "abc": [0.4948083, 0.18724296, 0.36456400999999994], "xyz": [7.6234643481336, 3.8004742912221605, 16.962412748003405], "label": "Cl", "properties": {}}, {"species": [{"element": "Cl", "occu": 1}], "abc": [0.44751874, 0.73279353, 0.30041674999999995], "xyz": [13.192705089830572, 14.873525667074132, 13.977772819411747], "label": "Cl", "properties": {}}, {"species": [{"element": "Cl", "occu": 1}], "abc": [0.80713638, 0.02756246, 0.34177125999999997], "xyz": [9.32962247082334, 0.55943582943166, 15.901913020775657], "label": "Cl", "properties": {}}, {"species": [{"element": "Cl", "occu": 1}], "abc": [0.75993655, 0.5724631, 0.2786057599999999], "xyz": [14.892601653352902, 11.619295562425101, 12.962952363540156], "label": "Cl", "properties": {}}, {"species": [{"element": "Cl", "occu": 1}], "abc": [0.13623932, 0.03742674, 0.3421372999999999], "xyz": [1.9411095274102599, 0.75965132774154, 15.918944108299296], "label": "Cl", "properties": {}}, {"species": [{"element": "Cl", "occu": 1}], "abc": [0.08996205, 0.58167152, 0.27924963999999997], "xyz": [7.507069599911801, 11.80619905654192, 12.992910774191238], "label": "Cl", "properties": {}}, {"species": [{"element": "Cl", "occu": 1}], "abc": [0.11356591, 0.88316051, 0.3202608699999999], "xyz": [11.14074177974343, 17.92552741784071, 14.901078863968666], "label": "Cl", "properties": {}}, {"species": [{"element": "Cl", "occu": 1}], "abc": [0.06659486, 0.4276253, 0.25809102999999994], "xyz": [5.52406144267658, 8.6795196942313, 12.008444216469227], "label": "Cl", "properties": {}}, {"species": [{"element": "Cl", "occu": 1}], "abc": [0.45709532, 0.88047558, 0.3196468599999999], "xyz": [14.95043793110806, 17.87103133724718, 14.872510242915256], "label": "Cl", "properties": {}}, {"species": [{"element": "Cl", "occu": 1}], "abc": [0.41268225, 0.42457035, 0.2576996], "xyz": [9.35821287852375, 8.61751330992735, 11.990231784523598], "label": "Cl", "properties": {}}, {"species": [{"element": "Cl", "occu": 1}], "abc": [0.31731198, 0.1786486, 0.29466498999999996], "xyz": [5.54348538355844, 3.6260343858206, 13.710155269485588], "label": "Cl", "properties": {}}, {"species": [{"element": "Cl", "occu": 1}], "abc": [0.36021668, 0.63400485, 0.35688027999999994], "xyz": [11.112714901886289, 12.86840975455185, 16.604904611903475], "label": "Cl", "properties": {}}, {"species": [{"element": "Cl", "occu": 1}], "abc": [0.65663879, 0.18123271, 0.29514956999999997], "xyz": [9.36510199442907, 3.67848412075691, 13.732701779135368], "label": "Cl", "properties": {}}, {"species": [{"element": "Cl", "occu": 1}], "abc": [0.6998988, 0.63719935, 0.3571890099999999], "xyz": [14.945125433252151, 12.933248588136351, 16.619269183128406], "label": "Cl", "properties": {}}, {"species": [{"element": "Cl", "occu": 1}], "abc": [0.64914378, 0.0242296, 0.27286211999999993], "xyz": [7.526450632253839, 0.4917887000216, 12.695712620494916], "label": "Cl", "properties": {}}, {"species": [{"element": "Cl", "occu": 1}], "abc": [0.69195133, 0.47960441, 0.33575894999999994], "xyz": [13.09480173440469, 9.73454078146261, 15.622172615821947], "label": "Cl", "properties": {}}, {"species": [{"element": "Cl", "occu": 1}], "abc": [0.30014176, 0.03410817, 0.27313385999999995], "xyz": [3.73599166724993, 0.69229424276157, 12.708356123182257], "label": "Cl", "properties": {}}, {"species": [{"element": "Cl", "occu": 1}], "abc": [0.34317311, 0.48908845, 0.3362655399999999], "xyz": [9.302434435104331, 9.92703854050745, 15.645743205453135], "label": "Cl", "properties": {}}, {"species": [{"element": "Cl", "occu": 1}], "abc": [0.97103697, 0.02326953, 0.27187300999999997], "xyz": [11.11359317491701, 0.47230213907013, 12.649691368772409], "label": "Cl", "properties": {}}, {"species": [{"element": "Cl", "occu": 1}], "abc": [0.01435587, 0.47828488, 0.3344452399999999], "xyz": [5.50641394417196, 9.707758253342481, 15.561048394450836], "label": "Cl", "properties": {}}, {"species": [{"element": "Cl", "occu": 1}], "abc": [0.39336558, 0.78512677, 0.37586995999999995], "xyz": [13.17236955203789, 15.93573453835217, 17.48845532255236], "label": "Cl", "properties": {}}, {"species": [{"element": "Cl", "occu": 1}], "abc": [0.35196978, 0.32883872, 0.31434951999999994], "xyz": [7.60959030296824, 6.67444640545312, 14.626035919938317], "label": "Cl", "properties": {}}, {"species": [{"element": "Cl", "occu": 1}], "abc": [0.99386687, 0.17935501, 0.29084787999999995], "xyz": [13.11338943188481, 3.6403724044252104, 13.532553000615078], "label": "Cl", "properties": {}}, {"species": [{"element": "Cl", "occu": 1}], "abc": [0.03562657, 0.6351721, 0.35327592999999996], "xyz": [7.497743991822461, 12.892101452314101, 16.43720162776013], "label": "Cl", "properties": {}}, {"species": [{"element": "Cl", "occu": 1}], "abc": [0.04484193, 0.7911791, 0.3743101999999999], "xyz": [9.344490233059542, 16.0585788074611, 17.415882901298197], "label": "Cl", "properties": {}}, {"species": [{"element": "Cl", "occu": 1}], "abc": [0.99922897, 0.33504775, 0.31250135999999995], "xyz": [14.913554315118908, 6.80047121775275, 14.540044840499757], "label": "Cl", "properties": {}}, {"species": [{"element": "Cl", "occu": 1}], "abc": [0.70929915, 0.78786969, 0.37410600999999993], "xyz": [16.73428965992925, 15.99140764319349, 17.406382361025408], "label": "Cl", "properties": {}}, {"species": [{"element": "Cl", "occu": 1}], "abc": [0.66567474, 0.33204799, 0.31180041], "xyz": [11.151813283607272, 6.7395850260377905, 14.507431080255808], "label": "Cl", "properties": {}}, {"species": [{"element": "Cl", "occu": 1}], "abc": [0.24249223, 0.0920189, 0.49430858999999994], "xyz": [3.7389179347589403, 1.8677095456969002, 22.999160911313187], "label": "Cl", "properties": {}}, {"species": [{"element": "Cl", "occu": 1}], "abc": [0.19157072, 0.63643559, 0.42753041999999997], "xyz": [9.25488977527271, 12.917746535377391, 19.89211015746522], "label": "Cl", "properties": {}}, {"species": [{"element": "Cl", "occu": 1}], "abc": [0.90380228, 0.0974002, 0.49317064999999993], "xyz": [11.19067978894884, 1.9769339048042003, 22.946214906131647], "label": "Cl", "properties": {}}, {"species": [{"element": "Cl", "occu": 1}], "abc": [0.8522692, 0.64112874, 0.42914637999999994], "xyz": [16.692124282172898, 13.01300349948354, 19.967297449003578], "label": "Cl", "properties": {}}, {"species": [{"element": "Cl", "occu": 1}], "abc": [0.87887112, 0.79425793, 0.4490804299999999], "xyz": [18.70103779345121, 16.121069884626532, 20.894787751294626], "label": "Cl", "properties": {}}, {"species": [{"element": "Cl", "occu": 1}], "abc": [0.84035623, 0.3342345, 0.38723815999999994], "xyz": [13.12870750133294, 6.7839646654245005, 18.017394261428556], "label": "Cl", "properties": {}}, {"species": [{"element": "Cl", "occu": 1}], "abc": [0.53889107, 0.9528572, 0.4689339699999999], "xyz": [16.67372201668796, 19.3401625984012, 21.818532089055765], "label": "Cl", "properties": {}}, {"species": [{"element": "Cl", "occu": 1}], "abc": [0.5013977, 0.49368017, 0.40608718999999993], "xyz": [11.122269991324249, 10.02023677777357, 18.894400817175786], "label": "Cl", "properties": {}}, {"species": [{"element": "Cl", "occu": 1}], "abc": [0.57798722, 0.10158795, 0.49209222999999996], "xyz": [7.59577850401891, 2.06193275449695, 22.896038243998426], "label": "Cl", "properties": {}}, {"species": [{"element": "Cl", "occu": 1}], "abc": [0.53407144, 0.64279311, 0.42511787999999995], "xyz": [13.15415860726127, 13.046785252325309, 19.77985963868508], "label": "Cl", "properties": {}}, {"species": [{"element": "Cl", "occu": 1}], "abc": [0.88979211, 0.94227209, 0.46835098999999997], "xyz": [20.47750951987213, 19.12531639844389, 21.791407230011586], "label": "Cl", "properties": {}}, {"species": [{"element": "Cl", "occu": 1}], "abc": [0.85297512, 0.48050163, 0.40356762999999996], "xyz": [14.904629886139709, 9.75275167464423, 18.77717087814983], "label": "Cl", "properties": {}}, {"species": [{"element": "Cl", "occu": 1}], "abc": [0.22217311, 0.94933679, 0.46870139999999993], "xyz": [13.09434432896163, 19.26870876270259, 21.807711085817395], "label": "Cl", "properties": {}}, {"species": [{"element": "Cl", "occu": 1}], "abc": [0.1828786, 0.49025139, 0.4043828199999999], "xyz": [7.52378473128035, 9.95064275810919, 18.815099990373614], "label": "Cl", "properties": {}}, {"species": [{"element": "Cl", "occu": 1}], "abc": [0.19423446, 0.79777141, 0.44589688999999993], "xyz": [11.08796912558333, 16.19238306196961, 20.746664190003486], "label": "Cl", "properties": {}}, {"species": [{"element": "Cl", "occu": 1}], "abc": [0.16015659, 0.33737356, 0.38384499999999994], "xyz": [5.56104739613072, 6.8476782321647605, 17.859517513144997], "label": "Cl", "properties": {}}, {"species": [{"element": "Cl", "occu": 1}], "abc": [0.53694439, 0.7944748, 0.44316750999999993], "xyz": [14.88166880375692, 16.125471699570802, 20.619671758396905], "label": "Cl", "properties": {}}, {"species": [{"element": "Cl", "occu": 1}], "abc": [0.50543832, 0.33411641, 0.38305895999999995], "xyz": [9.38393372730841, 6.78156779021461, 17.822944690401357], "label": "Cl", "properties": {}}, {"species": [{"element": "Cl", "occu": 1}], "abc": [0.4086176, 0.08894877, 0.42053858999999993], "xyz": [5.56142316962845, 1.80539505261417, 19.566794703743188], "label": "Cl", "properties": {}}, {"species": [{"element": "Cl", "occu": 1}], "abc": [0.44523214, 0.54897214, 0.48210090999999994], "xyz": [11.11251214587622, 11.142499053994941, 22.431162696526307], "label": "Cl", "properties": {}}, {"species": [{"element": "Cl", "occu": 1}], "abc": [0.74684601, 0.09184537, 0.4207638899999999], "xyz": [9.37425552180293, 1.86418740364277, 19.577277448850484], "label": "Cl", "properties": {}}, {"species": [{"element": "Cl", "occu": 1}], "abc": [0.79267142, 0.54326651, 0.48049427999999994], "xyz": [14.932146399639711, 11.026691762066712, 22.356409510677477], "label": "Cl", "properties": {}}, {"species": [{"element": "Cl", "occu": 1}], "abc": [0.73744343, 0.934892, 0.39811582999999995], "xyz": [18.69218377595204, 18.975522556732, 18.523509849406025], "label": "Cl", "properties": {}}, {"species": [{"element": "Cl", "occu": 1}], "abc": [0.78621513, 0.38887077, 0.46107573999999996], "xyz": [13.13424852176529, 7.89291818497617, 21.452904827251338], "label": "Cl", "properties": {}}, {"species": [{"element": "Cl", "occu": 1}], "abc": [0.38803586, 0.94528721, 0.39843916999999995], "xyz": [14.90296654965353, 19.18651435240141, 18.538554193848967], "label": "Cl", "properties": {}}, {"species": [{"element": "Cl", "occu": 1}], "abc": [0.43907346, 0.39784548, 0.46088885999999996], "xyz": [9.35448035781948, 8.07507806231508, 21.444209685637258], "label": "Cl", "properties": {}}, {"species": [{"element": "Cl", "occu": 1}], "abc": [0.05901433, 0.93441141, 0.3974698199999999], "xyz": [11.10385532318369, 18.96576801140961, 18.493452334240615], "label": "Cl", "properties": {}}, {"species": [{"element": "Cl", "occu": 1}], "abc": [0.10706114, 0.38799925, 0.46086861999999995], "xyz": [5.533448248711171, 7.875228925234251, 21.443267960111417], "label": "Cl", "properties": {}}, {"species": [{"element": "Cl", "occu": 1}], "abc": [0.46956571, 0.70393649, 0.49831166999999993], "xyz": [13.11658400847093, 14.287813720196292, 23.185415981371467], "label": "Cl", "properties": {}}, {"species": [{"element": "Cl", "occu": 1}], "abc": [0.44326521, 0.23864938, 0.44054938999999993], "xyz": [7.62194277093398, 4.84387147749698, 20.497856025505985], "label": "Cl", "properties": {}}, {"species": [{"element": "Cl", "occu": 1}], "abc": [0.08366671, 0.08982517, 0.41657771999999993], "xyz": [1.9391688084535301, 1.82318336181857, 19.382503578074516], "label": "Cl", "properties": {}}, {"species": [{"element": "Cl", "occu": 1}], "abc": [0.1176191, 0.5465828, 0.4791345699999999], "xyz": [7.424000024520801, 11.094002569838802, 22.293145004020367], "label": "Cl", "properties": {}}, {"species": [{"element": "Cl", "occu": 1}], "abc": [0.1348371, 0.70112154, 0.50010828], "xyz": [9.3437823490701, 14.230678620932341, 23.269008545451477], "label": "Cl", "properties": {}}, {"species": [{"element": "Cl", "occu": 1}], "abc": [0.09516276, 0.2447673, 0.43897675999999997], "xyz": [3.79950442244778, 4.9680470282133005, 20.424684789651156], "label": "Cl", "properties": {}}, {"species": [{"element": "Cl", "occu": 1}], "abc": [0.79369682, 0.70308068, 0.50031695], "xyz": [16.72990564320956, 14.27044332665428, 23.27871753089995], "label": "Cl", "properties": {}}, {"species": [{"element": "Cl", "occu": 1}], "abc": [0.75572475, 0.24226062, 0.4378140099999999], "xyz": [11.1547383656469, 4.91716889161302, 20.370584426253405], "label": "Cl", "properties": {}}, {"species": [{"element": "Cl", "occu": 1}], "abc": [0.28217704, 0.55065348, 0.56945072], "xyz": [9.30880103385572, 11.17662524728308, 26.495369502567517], "label": "Cl", "properties": {}}, {"species": [{"element": "Cl", "occu": 1}], "abc": [0.92561203, 0.55747801, 0.5588356], "xyz": [16.57690074653629, 11.31514287600821, 26.001469825499598], "label": "Cl", "properties": {}}, {"species": [{"element": "Cl", "occu": 1}], "abc": [0.91114487, 0.72504945, 0.5802444], "xyz": [18.288201797730608, 14.71634391268845, 26.9975772087804], "label": "Cl", "properties": {}}, {"species": [{"element": "Cl", "occu": 1}], "abc": [0.92781157, 0.24720552, 0.51479811], "xyz": [13.13346284187236, 5.01753563075592, 23.95249608899151], "label": "Cl", "properties": {}}, {"species": [{"element": "Cl", "occu": 1}], "abc": [0.58897094, 0.40784898, 0.5319581499999999], "xyz": [11.14173123911242, 8.278119311888581, 24.750917417669143], "label": "Cl", "properties": {}}, {"species": [{"element": "Cl", "occu": 1}], "abc": [0.60704661, 0.54983159, 0.54653659], "xyz": [12.930755739925631, 11.159943328693391, 25.429222213861188], "label": "Cl", "properties": {}}, {"species": [{"element": "Cl", "occu": 1}], "abc": [0.88201195, 0.88396263, 0.5941340199999999], "xyz": [19.73880394649195, 17.94180806432523, 27.643832628652817], "label": "Cl", "properties": {}}, {"species": [{"element": "Cl", "occu": 1}], "abc": [0.9378335, 0.39481795, 0.53169477], "xyz": [14.89539529488075, 8.01362822232695, 24.73866288856857], "label": "Cl", "properties": {}}, {"species": [{"element": "Cl", "occu": 1}], "abc": [0.56227895, 0.85375499, 0.60092907], "xyz": [15.827434092452151, 17.32868296088479, 27.959992314144866], "label": "Cl", "properties": {}}, {"species": [{"element": "Cl", "occu": 1}], "abc": [0.25285934, 0.39930356, 0.5396624999999999], "xyz": [7.28942014495772, 8.10467274269476, 25.109384959912497], "label": "Cl", "properties": {}}, {"species": [{"element": "Cl", "occu": 1}], "abc": [0.25136603, 0.24910722, 0.51500094], "xyz": [5.5939327686957405, 5.05613447559162, 23.961933351264538], "label": "Cl", "properties": {}}, {"species": [{"element": "Cl", "occu": 1}], "abc": [0.5827744, 0.6866804, 0.5856485699999999], "xyz": [14.1890660769012, 13.9375664990884, 27.249022111694366], "label": "Cl", "properties": {}}, {"species": [{"element": "Cl", "occu": 1}], "abc": [0.58233143, 0.24998885, 0.51266952], "xyz": [9.303062787279291, 5.07402893821585, 23.853457179058317], "label": "Cl", "properties": {}}, {"species": [{"element": "Cl", "occu": 1}], "abc": [0.49780212, 0.00125721, 0.55119438], "xyz": [5.578100064030809, 0.02551761777141, 25.64593959217158], "label": "Cl", "properties": {}}, {"species": [{"element": "Cl", "occu": 1}], "abc": [0.82866608, 0.01351943, 0.5469619699999999], "xyz": [9.41330104533959, 0.27440415461803, 25.449014269403765], "label": "Cl", "properties": {}}, {"species": [{"element": "Cl", "occu": 1}], "abc": [0.83540462, 0.47026985, 0.6101698499999999], "xyz": [14.59387626654161, 9.54507702111685, 28.389946780778846], "label": "Cl", "properties": {}}, {"species": [{"element": "Cl", "occu": 1}], "abc": [0.8097015, 0.85136383, 0.5217620599999999], "xyz": [18.56620552587335, 17.280149536150432, 24.276514343718457], "label": "Cl", "properties": {}}, {"species": [{"element": "Cl", "occu": 1}], "abc": [0.87200537, 0.29826812, 0.5896157599999999], "xyz": [13.08044851745576, 6.053954295270521, 27.433607293950157], "label": "Cl", "properties": {}}, {"species": [{"element": "Cl", "occu": 1}], "abc": [0.48237451, 0.8553586, 0.52351702], "xyz": [14.95224805057528, 17.3612314667306, 24.35816901905582], "label": "Cl", "properties": {}}, {"species": [{"element": "Cl", "occu": 1}], "abc": [0.52236345, 0.31339325, 0.5880153899999999], "xyz": [9.34147985543785, 6.36094937650825, 27.359145373011984], "label": "Cl", "properties": {}}, {"species": [{"element": "Cl", "occu": 1}], "abc": [0.11832969, 0.8505406, 0.52772559], "xyz": [10.82938364700632, 17.2634404195526, 24.553985115710187], "label": "Cl", "properties": {}}, {"species": [{"element": "Cl", "occu": 1}], "abc": [0.18044865, 0.30156111, 0.5893455999999999], "xyz": [5.38756826839515, 6.120792182453311, 27.421037305409595], "label": "Cl", "properties": {}}, {"species": [{"element": "Cl", "occu": 1}], "abc": [0.51907328, 0.1551661, 0.56859865], "xyz": [7.53614543127234, 3.1494095901881, 26.45572443987965], "label": "Cl", "properties": {}}, {"species": [{"element": "Cl", "occu": 1}], "abc": [0.1778343, 0.99542033, 0.54428523], "xyz": [13.11385096574425, 20.20406734183693, 25.324471068611427], "label": "Cl", "properties": {}}, {"species": [{"element": "Cl", "occu": 1}], "abc": [0.19223799, 0.44964517, 0.61413124], "xyz": [7.17452703716537, 9.126457458038571, 28.57426210097684], "label": "Cl", "properties": {}}, {"species": [{"element": "Cl", "occu": 1}], "abc": [0.18488706, 0.15072173, 0.567754], "xyz": [3.75119359907653, 3.05920211896633, 26.416424614514], "label": "Cl", "properties": {}}, {"species": [{"element": "Cl", "occu": 1}], "abc": [0.84146394, 0.15737565, 0.5656280899999999], "xyz": [11.16427624580757, 3.1942568729386505, 26.317510399462684], "label": "Cl", "properties": {}}]}, "formula": "(Li3YCl6)26.0(LiCl)12.0", "bandgap": 4.429, "slab_thickness": 28.56960930687684}