{"miller": "130_0.14", "final_energy": -741.63093856, "gamma": 0.022698449806546193, "work_function": 4.501493934031122, "ionization_potentail": -4.867593934031122, "electron_affinity": -3.063593934031122, "is_stochiometric": false, "incar_parameters": {"SYSTEM": "unknown system", "LCOMPAT": false, "PREC": "normal", "ENMAX": 520.0, "ENAUG": 628.945, "EDIFF": 1e-05, "IALGO": 38, "IWAVPR": 11, "NBANDS": 508, "NBANDSLOW": -1, "NBANDSHIGH": -1, "NELECT": 832.0, "TURBO": 0, "IRESTART": 0, "NREBOOT": 0, "NMIN": 0, "EREF": 0.0, "ISMEAR": 0, "SIGMA": 0.05, "KSPACING": 0.5, "KGAMMA": true, "KBLOWUP": true, "LREAL": true, "ROPT": [-0.0005, -0.0005, -0.0005, -0.0005], "LMAXPAW": -100, "LMAXMIX": 2, "NLSPLINE": false, "ISTART": 0, "ICHARG": 2, "INIWAV": 1, "ISPIN": 1, "LNONCOLLINEAR": false, "MAGMOM": [0.6, 0.6, 0.6, 0.6, 0.6, 0.6, 0.6, 0.6, 0.6, 0.6, 0.6, 0.6, 0.6, 0.6, 0.6, 0.6, 0.6, 0.6, 0.6, 0.6, 0.6, 0.6, 0.6, 0.6, 0.6, 0.6, 0.6, 0.6, 0.6, 0.6, 0.6, 0.6, 0.6, 0.6, 0.6, 0.6, 0.6, 0.6, 0.6, 0.6, 0.6, 0.6, 0.6, 0.6, 0.6, 0.6, 0.6, 0.6, 0.6, 0.6, 0.6, 0.6, 0.6, 0.6, 0.6, 0.6, 0.6, 0.6, 0.6, 0.6, 0.6, 0.6, 0.6, 0.6, 0.6, 0.6, 0.6, 0.6, 0.6, 0.6, 0.6, 0.6, 0.6, 0.6, 0.6, 0.6, 0.6, 0.6, 0.6, 0.6, 0.6, 0.6, 0.6, 0.6, 0.6, 0.6, 0.6, 0.6, 0.6, 0.6, 0.6, 0.6, 0.6, 0.6, 0.6, 0.6, 0.6, 0.6, 0.6, 0.6, 0.6, 0.6, 0.6, 0.6, 0.6, 0.6, 0.6, 0.6, 0.6, 0.6, 0.6, 0.6, 0.6, 0.6, 0.6, 0.6, 0.6, 0.6, 0.6, 0.6, 0.6, 0.6, 0.6, 0.6, 0.6, 0.6, 0.6, 0.6, 0.6, 0.6, 0.6, 0.6, 0.6, 0.6, 0.6, 0.6, 0.6, 0.6, 0.6, 0.6, 0.6, 0.6, 0.6, 0.6, 0.6, 0.6, 0.6, 0.6, 0.6, 0.6, 0.6, 0.6, 0.6, 0.6, 0.6, 0.6, 0.6, 0.6, 0.6, 0.6, 0.6, 0.6, 0.6, 0.6, 0.6, 0.6, 0.6, 0.6, 0.6, 0.6, 0.6, 0.6, 0.6, 0.6, 0.6, 0.6, 0.6, 0.6, 0.6, 0.6, 0.6, 0.6], "NUPDOWN": -1.0, "LSORBIT": false, "SAXIS": [0.0, 0.0, 1.0], "LSPIRAL": false, "QSPIRAL": [0.0, 0.0, 0.0], "LZEROZ": false, "LASPH": false, "LMETAGGA": false, "NELM": 100, "NELMDL": -5, "NELMIN": 6, "ENINI": 520.0, "LDIAG": true, "LSUBROT": false, "WEIMIN": 0.001, "EBREAK": 0.0, "DEPER": 0.3, "NRMM": 4, "TIME": 0.4, "AMIX": 0.4, "BMIX": 1.0, "AMIN": 0.1, "AMIX_MAG": 1.6, "BMIX_MAG": 1.0, "IMIX": 4, "MIXFIRST": false, "MAXMIX": -45, "WC": 100.0, "INIMIX": 1, "MIXPRE": 1, "MREMOVE": 5, "LDIPOL": false, "LMONO": false, "IDIPOL": 0, "EPSILON": 1.0, "DIPOL": [-100.0, -100.0, -100.0], "EFIELD": 0.0, "NGX": 60, "NGY": 120, "NGZ": 224, "NGXF": 120, "NGYF": 240, "NGZF": 448, "ADDGRID": false, "NSW": 150, "IBRION": 2, "MDALGO": 0, "ISIF": 2, "PSTRESS": 0.0, "EDIFFG": -0.01, "NFREE": 1, "POTIM": 0.5, "SMASS": -3.0, "SCALEE": 1.0, "TEBEG": 0.0001, "TEEND": 0.0001, "NBLOCK": 1, "KBLOCK": 150, "NPACO": 256, "APACO": 10.0, "ISYM": 0, "SYMPREC": 1e-05, "LORBIT": 11, "RWIGS": [-1.0, -1.0, -1.0, -1.0], "NEDOS": 301, "EMIN": 10.0, "EMAX": -10.0, "EFERMI": 0.0, "NWRITE": 2, "LWAVE": false, "LDOWNSAMPLE": false, "LCHARG": false, "LPARD": false, "LVTOT": false, "LVHAR": false, "LELF": false, "LOPTICS": false, "STM": [0.0, 0.0, 0.0, 0.0, 0.0, 0.0, 0.0], "NPAR": 2, "NSIM": 1, "NBLK": -1, "LPLANE": true, "LSCALAPACK": true, "LSCAAWARE": false, "LSCALU": false, "LASYNC": false, "LORBITALREAL": false, "IDIOT": 3, "PHON_NSTRUCT": -1, "LMUSIC": false, "POMASS": [7.01, 30.974, 32.066, 35.453], "DARWINR": [0.0, 0.0, 0.0, 0.0], "DARWINV": [1.0, 1.0, 1.0, 1.0], "LCORR": true, "GGA_COMPAT": true, "LBERRY": false, "ICORELEVEL": 0, "LDAU": false, "I_CONSTRAINED_M": 0, "GGA": "--", "VOSKOWN": 0, "LHFCALC": false, "PRECFOCK": "", "LSYMGRAD": false, "LHFONE": false, "LRHFCALC": false, "LTHOMAS": false, "LMODELHF": false, "LFOCKACE": false, "ENCUT4O": -1.0, "EXXOEP": 0, "FOURORBIT": 0, "AEXX": 0.0, "HFALPHA": 0.0, "MCALPHA": 0.0, "ALDAX": 1.0, "AGGAX": 1.0, "ALDAC": 1.0, "AGGAC": 1.0, "NKREDX": 1, "NKREDY": 1, "NKREDZ": 1, "SHIFTRED": false, "ODDONLY": false, "EVENONLY": false, "LMAXFOCK": 0, "NMAXFOCKAE": 0, "LFOCKAEDFT": false, "HFSCREEN": 0.0, "HFSCREENC": 0.0, "NBANDSGWLOW": 0, "LUSE_VDW": false, "Zab_VDW": -0.8491, "PARAM1": 0.1234, "PARAM2": 1.0, "PARAM3": 0.0, "MODEL_GW": 0, "MODEL_EPS0": 30.19858098, "MODEL_ALPHA": 1.0, "LEPSILON": false, "LRPA": false, "LNABLA": false, "LVEL": false, "CSHIFT": 0.1, "OMEGAMAX": -1.0, "DEG_THRESHOLD": 0.002, "RTIME": -0.1, "WPLASMAI": 0.0, "DFIELD": [0.0, 0.0, 0.0], "WPLASMA": [0.0, 0.0, 0.0, 0.0, 0.0, 0.0, 0.0, 0.0, 0.0], "NUCIND": false, "MAGPOS": [0.0, 0.0, 0.0], "LNICSALL": true, "ORBITALMAG": false, "LMAGBLOCH": false, "LCHIMAG": false, "LGAUGE": true, "MAGATOM": 0, "MAGDIPOL": [0.0, 0.0, 0.0], "AVECCONST": [0.0, 0.0, 0.0], "LFINITE_TEMPERATURE": false, "LADDER": false, "LRPAFORCE": false, "LFXC": false, "LHARTREE": true, "IBSE": 0, "KPOINT": [-1, 0, 0, 0], "LTCTC": false, "LTCTE": false, "LTETE": false, "LTRIPLET": false, "LFXCEPS": false, "LFXHEG": false, "NATURALO": 2, "LHOLEGF": false, "L2ORDER": false, "LDMP1": false, "LMP2LT": false, "LSMP2LT": false, "LGWLF": false, "ENCUTGW": -2.0, "ENCUTGWSOFT": -2.0, "ENCUTLF": -1.0, "LESF_SPLINES": false, "LMAXMP2": -1, "SCISSOR": 0.0, "NOMEGA": 0, "NOMEGAR": 0, "NBANDSGW": -1, "NBANDSO": -1, "NBANDSV": -1, "NELMGW": 1, "NELMHF": 1, "DIM": 3, "IESPILON": 4, "ANTIRES": 0, "OMEGAMIN": -30.0, "OMEGATL": -200.0, "OMEGAGRID": 0, "LSELFENERGY": false, "LSPECTRAL": false, "LSPECTRALGW": false, "LSINGLES": false, "LFERMIGW": false, "ODDONLYGW": false, "EVENONLYGW": false, "NKREDLFX": 1, "NKREDLFY": 1, "NKREDLFZ": 1, "MAXMEM": 2800, "TELESCOPE": 0, "NTAUPAR": -1, "NOMEGAPAR": -1, "DAMP_NEWTON": 0.80000001, "LAMBDA": 1.0, "OFIELD_KAPPA": 0.0, "OFIELD_K": [0.0, 0.0, 0.0], "OFIELD_Q6_NEAR": 0.0, "OFIELD_Q6_FAR": 0.0, "OFIELD_A": 0.0, "KPOINTS_OPT_MODE": 1, "LKPOINTS_OPT": false, "@module": "pymatgen.io.vasp.inputs", "@class": "Incar"}, "relaxed_structures": {"@module": "pymatgen.core.structure", "@class": "Structure", "charge": 0, "lattice": {"matrix": [[10.604103, 0.0, 0.0], [0.0, 21.511033, 0.0], [0.0, 0.0, 40.157944]], "a": 10.604103, "b": 21.511033, "c": 40.157944, "alpha": 90.0, "beta": 90.0, "gamma": 90.0, "volume": 9160.23623195603}, "sites": [{"species": [{"element": "Li", "occu": 1}], "abc": [0.76703046, 0.13793526, 0.08822827999999999], "xyz": [8.13367000197738, 2.9671299297235803, 3.54306632745632], "label": "Li", "properties": {}}, {"species": [{"element": "Li", "occu": 1}], "abc": [0.62040564, 0.48226462, 0.00013325000000000836], "xyz": [6.57884530834092, 10.37401015555246, 0.0053510460380003354], "label": "Li", "properties": {}}, {"species": [{"element": "Li", "occu": 1}], "abc": [0.80775461, 0.84599996, 0.11915355000000002], "xyz": [8.56551308316483, 18.19833305755868, 4.784961588301201], "label": "Li", "properties": {}}, {"species": [{"element": "Li", "occu": 1}], "abc": [0.7924618, 0.34898865, 0.09032938000000001], "xyz": [8.4033465507654, 7.50710636677545, 3.6274421835947206], "label": "Li", "properties": {}}, {"species": [{"element": "Li", "occu": 1}], "abc": [0.9287231, 0.6115924, 0.03588602000000001], "xyz": [9.848275410879301, 13.155984298949202, 1.4411087815428805], "label": "Li", "properties": {}}, {"species": [{"element": "Li", "occu": 1}], "abc": [0.98710255, 0.25428439, 0.06731888999999999], "xyz": [10.467337111762651, 5.469919904674871, 2.7033882147621595], "label": "Li", "properties": {}}, {"species": [{"element": "Li", "occu": 1}], "abc": [0.64636016, 0.64819065, 0.016941390000000008], "xyz": [6.8540697117364795, 13.94325046244145, 0.6803313909021603], "label": "Li", "properties": {}}, {"species": [{"element": "Li", "occu": 1}], "abc": [0.79604065, 0.99588083, 0.08692434000000002], "xyz": [8.44129704478695, 21.422425398197394, 3.490702777956961], "label": "Li", "properties": {}}, {"species": [{"element": "Li", "occu": 1}], "abc": [0.72231347, 0.22826172, 0.13526604], "xyz": [7.659486434167411, 4.91014539155676, 5.43200605942176], "label": "Li", "properties": {}}, {"species": [{"element": "Li", "occu": 1}], "abc": [0.82440631, 0.48169888, 0.06309196], "xyz": [8.74208942508993, 10.361840503743041, 2.5336433965302403], "label": "Li", "properties": {}}, {"species": [{"element": "Li", "occu": 1}], "abc": [0.83639816, 0.7600767, 0.014049680000000002], "xyz": [8.86925223765048, 16.3500349762311, 0.5642062626579201], "label": "Li", "properties": {}}, {"species": [{"element": "Li", "occu": 1}], "abc": [0.30782506, 0.34601846, 0.11915914000000002], "xyz": [3.26420864222118, 7.443214511669181, 4.785186071208161], "label": "Li", "properties": {}}, {"species": [{"element": "Li", "occu": 1}], "abc": [0.26707342, 0.63792778, 0.08822470000000002], "xyz": [2.83207405424226, 13.722485527196742, 3.5429225620168006], "label": "Li", "properties": {}}, {"species": [{"element": "Li", "occu": 1}], "abc": [0.1203766, 0.98231544, 0.00010000000000000286], "xyz": [1.2764858651898001, 21.130619846249523, 0.004015794400000115], "label": "Li", "properties": {}}, {"species": [{"element": "Li", "occu": 1}], "abc": [0.42868934, 0.11159735, 0.03589035000000001], "xyz": [4.54586591636202, 2.40057427856255, 1.4412826654404003], "label": "Li", "properties": {}}, {"species": [{"element": "Li", "occu": 1}], "abc": [0.29241201, 0.8489989, 0.09033218000000001], "xyz": [3.10076707247703, 18.2628433548637, 3.6275546258379205], "label": "Li", "properties": {}}, {"species": [{"element": "Li", "occu": 1}], "abc": [0.14631058, 0.14819467, 0.016963320000000004], "xyz": [1.55149246030974, 3.18782043679411, 0.6812120546140802], "label": "Li", "properties": {}}, {"species": [{"element": "Li", "occu": 1}], "abc": [0.29606516, 0.49586028, 0.08692458], "xyz": [3.13950545135148, 10.666466846469241, 3.49071241586352], "label": "Li", "properties": {}}, {"species": [{"element": "Li", "occu": 1}], "abc": [0.4871552, 0.75423899, 0.06733346000000001], "xyz": [5.1658439177856, 16.22445980377667, 2.7039733160062407], "label": "Li", "properties": {}}, {"species": [{"element": "Li", "occu": 1}], "abc": [0.33637224, 0.26008096, 0.014042740000000005], "xyz": [3.56692587930072, 5.594610113231681, 0.5639275665265602], "label": "Li", "properties": {}}, {"species": [{"element": "Li", "occu": 1}], "abc": [0.22234466, 0.72826222, 0.13526813000000001], "xyz": [2.35776567613998, 15.66567264707326, 5.43208998952472], "label": "Li", "properties": {}}, {"species": [{"element": "Li", "occu": 1}], "abc": [0.32446795, 0.98172166, 0.06308936000000001], "xyz": [3.4406915619988503, 21.11784702507478, 2.5335389858758406], "label": "Li", "properties": {}}, {"species": [{"element": "Li", "occu": 1}], "abc": [0.0780558, 0.0332588, 0.06671867000000001], "xyz": [0.8277117429474, 0.7154311443404, 2.6792846136144806], "label": "Li", "properties": {}}, {"species": [{"element": "Li", "occu": 1}], "abc": [0.15826566, 0.34886117, 0.03775857], "xyz": [1.67826536000298, 7.504364140288611, 1.5163065395800799], "label": "Li", "properties": {}}, {"species": [{"element": "Li", "occu": 1}], "abc": [0.03347269, 0.7371108, 0.06895804999999999], "xyz": [0.35494785244707, 15.8560147434564, 2.7692135102492], "label": "Li", "properties": {}}, {"species": [{"element": "Li", "occu": 1}], "abc": [0.03969618, 0.42812899, 0.1083586], "xyz": [0.42094238142654, 9.20949683214667, 4.3514585907184005], "label": "Li", "properties": {}}, {"species": [{"element": "Li", "occu": 1}], "abc": [0.19882347, 0.7677809, 0.021605430000000002], "xyz": [2.10834455469741, 16.5157602766697, 0.8676296480359201], "label": "Li", "properties": {}}, {"species": [{"element": "Li", "occu": 1}], "abc": [0.53348267, 0.23699207, 0.06901750000000001], "xyz": [5.657105181395011, 5.09794423850831, 2.7716009000200006], "label": "Li", "properties": {}}, {"species": [{"element": "Li", "occu": 1}], "abc": [0.57807121, 0.53328028, 0.06674925000000001], "xyz": [6.129926652174629, 11.471409701329241, 2.6805126435420004], "label": "Li", "properties": {}}, {"species": [{"element": "Li", "occu": 1}], "abc": [0.65823156, 0.84887232, 0.03774294000000001], "xyz": [6.979955260090681, 18.260120488306562, 1.5156788709153604], "label": "Li", "properties": {}}, {"species": [{"element": "Li", "occu": 1}], "abc": [0.69872342, 0.26775131, 0.021614260000000003], "xyz": [7.40933511419226, 5.759607265203231, 0.8679842426814401], "label": "Li", "properties": {}}, {"species": [{"element": "Li", "occu": 1}], "abc": [0.53970828, 0.92812542, 0.10835430000000001], "xyz": [5.72312219107284, 19.96493653775886, 4.3512859115592], "label": "Li", "properties": {}}, {"species": [{"element": "Li", "occu": 1}], "abc": [0.80374342, 0.25226565, 0.23135563000000003], "xyz": [8.52297801125226, 5.42649472191645, 9.290766433624722], "label": "Li", "properties": {}}, {"species": [{"element": "Li", "occu": 1}], "abc": [0.77341994, 0.54682188, 0.1733657], "xyz": [8.201424706013821, 11.76270350580204, 6.9620100721208], "label": "Li", "properties": {}}, {"species": [{"element": "Li", "occu": 1}], "abc": [0.79560139, 0.94561144, 0.29485407], "xyz": [8.43663908650317, 20.34107889101752, 11.84073323123208], "label": "Li", "properties": {}}, {"species": [{"element": "Li", "occu": 1}], "abc": [0.80671813, 0.44857868, 0.2649868], "xyz": [8.554522142487391, 9.64939078857644, 10.641325075139202], "label": "Li", "properties": {}}, {"species": [{"element": "Li", "occu": 1}], "abc": [0.77745644, 0.74726253, 0.21123074], "xyz": [8.24422816777332, 16.074388942493492, 8.48259222799856], "label": "Li", "properties": {}}, {"species": [{"element": "Li", "occu": 1}], "abc": [0.81566338, 0.04127469, 0.15379737000000002], "xyz": [8.649378494848142, 0.8878612186547701, 6.176186171807281], "label": "Li", "properties": {}}, {"species": [{"element": "Li", "occu": 1}], "abc": [0.78829105, 0.40697907, 0.20027195], "xyz": [8.35911948817815, 8.75454020507931, 8.0425097528708], "label": "Li", "properties": {}}, {"species": [{"element": "Li", "occu": 1}], "abc": [0.82326932, 0.70285993, 0.14770945000000002], "xyz": [8.73003266601996, 15.11924314860769, 5.931707821370801], "label": "Li", "properties": {}}, {"species": [{"element": "Li", "occu": 1}], "abc": [0.71331014, 0.06431156, 0.24960503], "xyz": [7.564014195504421, 1.3834080894414802, 10.02362481685832], "label": "Li", "properties": {}}, {"species": [{"element": "Li", "occu": 1}], "abc": [0.79839716, 0.29804592, 0.29711142], "xyz": [8.46628571954748, 6.411275620635361, 11.931383766120481], "label": "Li", "properties": {}}, {"species": [{"element": "Li", "occu": 1}], "abc": [0.79746622, 0.59248839, 0.23842318], "xyz": [8.45641393590066, 12.74503730940687, 9.57458471074192], "label": "Li", "properties": {}}, {"species": [{"element": "Li", "occu": 1}], "abc": [0.79354897, 0.8887056, 0.18436376000000002], "xyz": [8.414875013423911, 19.1169754888848, 7.4036695497094405], "label": "Li", "properties": {}}, {"species": [{"element": "Li", "occu": 1}], "abc": [0.29563134, 0.44559618, 0.29482592], "xyz": [3.1349051793880203, 9.585234132653941, 11.83960278510848], "label": "Li", "properties": {}}, {"species": [{"element": "Li", "occu": 1}], "abc": [0.30327757, 0.75237936, 0.23145958], "xyz": [3.21598658986971, 16.18445724147888, 9.29494085190352], "label": "Li", "properties": {}}, {"species": [{"element": "Li", "occu": 1}], "abc": [0.27346038, 0.04680957, 0.17337335], "xyz": [2.8998020359391403, 1.0069222049858102, 6.9623172803924005], "label": "Li", "properties": {}}, {"species": [{"element": "Li", "occu": 1}], "abc": [0.27752808, 0.24715111, 0.21120191000000002], "xyz": [2.94293634571224, 5.31647568319663, 8.48143447447304], "label": "Li", "properties": {}}, {"species": [{"element": "Li", "occu": 1}], "abc": [0.3156983, 0.54128209, 0.15379544], "xyz": [3.3476972901249, 11.643536900298972, 6.17610866697536], "label": "Li", "properties": {}}, {"species": [{"element": "Li", "occu": 1}], "abc": [0.30673926, 0.94860175, 0.26499039], "xyz": [3.2526947071837804, 20.405403548107753, 10.641469242158161], "label": "Li", "properties": {}}, {"species": [{"element": "Li", "occu": 1}], "abc": [0.32319929, 0.20293025, 0.14770012000000002], "xyz": [3.42723856068687, 4.3652393044482505, 5.931333147753281], "label": "Li", "properties": {}}, {"species": [{"element": "Li", "occu": 1}], "abc": [0.21338004, 0.56427495, 0.24961318], "xyz": [2.26270392230412, 12.138137070523351, 10.02395210410192], "label": "Li", "properties": {}}, {"species": [{"element": "Li", "occu": 1}], "abc": [0.2882675, 0.90699042, 0.20027673000000001], "xyz": [3.0568182615525004, 19.51030085530386, 8.04270170784312], "label": "Li", "properties": {}}, {"species": [{"element": "Li", "occu": 1}], "abc": [0.29354121, 0.38868645, 0.18437296], "xyz": [3.11274122558463, 8.361047052602851, 7.40403900279424], "label": "Li", "properties": {}}, {"species": [{"element": "Li", "occu": 1}], "abc": [0.29840059, 0.79806078, 0.29712507], "xyz": [3.1642705916207703, 17.16711177458574, 11.93193192205608], "label": "Li", "properties": {}}, {"species": [{"element": "Li", "occu": 1}], "abc": [0.29695682, 0.09250592, 0.23850236000000002], "xyz": [3.1489607058324602, 1.9898978978153603, 9.577764416747842], "label": "Li", "properties": {}}, {"species": [{"element": "Li", "occu": 1}], "abc": [0.02748183, 0.15824416, 0.22156203000000002], "xyz": [0.29142015594848997, 3.40399534781728, 8.897475593266321], "label": "Li", "properties": {}}, {"species": [{"element": "Li", "occu": 1}], "abc": [0.03933531, 0.46256964, 0.16911025000000002], "xyz": [0.41711567877693, 9.95035079083812, 6.791119949326001], "label": "Li", "properties": {}}, {"species": [{"element": "Li", "occu": 1}], "abc": [0.04026325, 0.86533501, 0.27736576], "xyz": [0.42695565011475, 18.61424995616533, 11.13843865759744], "label": "Li", "properties": {}}, {"species": [{"element": "Li", "occu": 1}], "abc": [0.05798835, 0.15680969, 0.14867073], "xyz": [0.61491443620005, 3.37313841630977, 5.97031084977912], "label": "Li", "properties": {}}, {"species": [{"element": "Li", "occu": 1}], "abc": [0.03314522, 0.55799506, 0.3159402], "xyz": [0.35147532683766003, 12.00305014949698, 12.687508858948801], "label": "Li", "properties": {}}, {"species": [{"element": "Li", "occu": 1}], "abc": [0.03749736, 0.83515251, 0.21619426000000003], "xyz": [0.39762586766808, 17.96499320264283, 8.681916986201442], "label": "Li", "properties": {}}, {"species": [{"element": "Li", "occu": 1}], "abc": [0.54032899, 0.36532913, 0.27736001], "xyz": [5.72970426384597, 7.85860697129129, 11.13820774941944], "label": "Li", "properties": {}}, {"species": [{"element": "Li", "occu": 1}], "abc": [0.52745034, 0.65824642, 0.22163585000000002], "xyz": [5.593137732745021, 14.15956046275186, 8.900440052692401], "label": "Li", "properties": {}}, {"species": [{"element": "Li", "occu": 1}], "abc": [0.53933654, 0.96256933, 0.16911417], "xyz": [5.71918022182362, 20.70586062241789, 6.7912773684664804], "label": "Li", "properties": {}}, {"species": [{"element": "Li", "occu": 1}], "abc": [0.53751915, 0.33513458, 0.21619308000000004], "xyz": [5.6999084310724495, 7.209091009821141, 8.681869599827522], "label": "Li", "properties": {}}, {"species": [{"element": "Li", "occu": 1}], "abc": [0.55760206, 0.65714423, 0.14903813000000002], "xyz": [5.91286967725218, 14.135851217289591, 5.985064878404721], "label": "Li", "properties": {}}, {"species": [{"element": "Li", "occu": 1}], "abc": [0.53309199, 0.05799356, 0.31594252], "xyz": [5.652962370434969, 1.2475013829474801, 12.68760202537888], "label": "Li", "properties": {}}, {"species": [{"element": "Li", "occu": 1}], "abc": [0.92699168, 0.68325526, 0.34790608], "xyz": [9.82991525486304, 14.697526445283582, 13.97119287789952], "label": "Li", "properties": {}}, {"species": [{"element": "Li", "occu": 1}], "abc": [0.61668543, 0.81214626, 0.38404342], "xyz": [6.5393958183192895, 17.47010499968658, 15.422394153928481], "label": "Li", "properties": {}}, {"species": [{"element": "Li", "occu": 1}], "abc": [0.76837824, 0.1562147, 0.29493896000000003], "xyz": [8.14796199991872, 3.3603395667851004, 11.844142239098241], "label": "Li", "properties": {}}, {"species": [{"element": "Li", "occu": 1}], "abc": [0.83402101, 0.53554601, 0.36922885], "xyz": [8.84404469420403, 11.52014789412833, 14.8274714814844], "label": "Li", "properties": {}}, {"species": [{"element": "Li", "occu": 1}], "abc": [0.8219744, 0.81399348, 0.32169183], "xyz": [8.7163012009632, 17.509840610064842, 12.918482494397521], "label": "Li", "properties": {}}, {"species": [{"element": "Li", "occu": 1}], "abc": [0.64594813, 0.64745099, 0.36797254], "xyz": [6.84970050317739, 13.92733961177267, 14.777020654857761], "label": "Li", "properties": {}}, {"species": [{"element": "Li", "occu": 1}], "abc": [0.98592319, 0.04434508, 0.31586037], "xyz": [10.454831056848569, 0.9539084792676401, 12.684303050279281], "label": "Li", "properties": {}}, {"species": [{"element": "Li", "occu": 1}], "abc": [0.426986, 0.18325357, 0.34790299], "xyz": [4.527803523558, 3.9419735916378102, 13.971068789852561], "label": "Li", "properties": {}}, {"species": [{"element": "Li", "occu": 1}], "abc": [0.11662694, 0.31212788, 0.38404138], "xyz": [1.23672408433482, 6.7141931269000406, 15.422312231722719], "label": "Li", "properties": {}}, {"species": [{"element": "Li", "occu": 1}], "abc": [0.26843101, 0.65618084, 0.29495714], "xyz": [2.8464700784340304, 14.11512770320772, 11.844872310520161], "label": "Li", "properties": {}}, {"species": [{"element": "Li", "occu": 1}], "abc": [0.32224321, 0.31403375, 0.32180292], "xyz": [3.41710018989063, 6.75519035936375, 12.922943640396479], "label": "Li", "properties": {}}, {"species": [{"element": "Li", "occu": 1}], "abc": [0.33381579, 0.0355826, 0.36925279], "xyz": [3.53981702018637, 0.7654184828258, 14.82843286266376], "label": "Li", "properties": {}}, {"species": [{"element": "Li", "occu": 1}], "abc": [0.48654766, 0.54395588, 0.31623278], "xyz": [5.15940150104898, 11.701052885224039, 12.69925827020432], "label": "Li", "properties": {}}, {"species": [{"element": "Li", "occu": 1}], "abc": [0.14563685, 0.14731816, 0.36780679], "xyz": [1.5443481579955503, 3.1689658012592803, 14.77036447563976], "label": "Li", "properties": {}}, {"species": [{"element": "Li", "occu": 1}], "abc": [0.19839044, 0.52660304, 0.36300215], "xyz": [2.1037526599753202, 11.327775371340321, 14.577420011579601], "label": "Li", "properties": {}}, {"species": [{"element": "Li", "occu": 1}], "abc": [0.0798843, 0.26121161, 0.31670243000000003], "xyz": [0.8471013452829, 5.61893156269313, 12.71811844860392], "label": "Li", "properties": {}}, {"species": [{"element": "Li", "occu": 1}], "abc": [0.15594127, 0.94764632, 0.34499083], "xyz": [1.65361728903081, 20.384851261848564, 13.854122431653522], "label": "Li", "properties": {}}, {"species": [{"element": "Li", "occu": 1}], "abc": [0.69836405, 0.026607, 0.36299546], "xyz": [7.40552431769715, 0.572344055031, 14.577151354934239], "label": "Li", "properties": {}}, {"species": [{"element": "Li", "occu": 1}], "abc": [0.6560793, 0.44766543, 0.34502696], "xyz": [6.9571324733679, 9.62974583768919, 13.85557333817024], "label": "Li", "properties": {}}, {"species": [{"element": "Li", "occu": 1}], "abc": [0.57982661, 0.76121328, 0.31671138], "xyz": [6.14854109458083, 16.37448398611824, 12.71847786220272], "label": "Li", "properties": {}}, {"species": [{"element": "P", "occu": 1}], "abc": [0.51533871, 0.0921531, 0.10849897], "xyz": [5.4647047607271295, 1.9823083751523, 4.3570955613176805], "label": "P", "properties": {}}, {"species": [{"element": "P", "occu": 1}], "abc": [0.51232667, 0.39935113, 0.048061150000000004], "xyz": [5.43276477832701, 8.59045533601729, 1.9300369702756002], "label": "P", "properties": {}}, {"species": [{"element": "P", "occu": 1}], "abc": [0.01544362, 0.59216699, 0.10849152000000001], "xyz": [0.16376573717286, 12.73812366340067, 4.3567963846348805], "label": "P", "properties": {}}, {"species": [{"element": "P", "occu": 1}], "abc": [0.01238489, 0.89936446, 0.04803511], "xyz": [0.13133064920367002, 19.34625857808718, 1.92899125741384], "label": "P", "properties": {}}, {"species": [{"element": "P", "occu": 1}], "abc": [0.51415721, 0.20152722, 0.27548438000000003], "xyz": [5.452176013032631, 4.33505867981826, 11.062886304914722], "label": "P", "properties": {}}, {"species": [{"element": "P", "occu": 1}], "abc": [0.5073856, 0.49707419, 0.22257944000000002], "xyz": [5.3803691631168, 10.69257930453827, 8.93833268707136], "label": "P", "properties": {}}, {"species": [{"element": "P", "occu": 1}], "abc": [0.5102772, 0.79741612, 0.16328589000000002], "xyz": [5.4110319873516, 17.15324447205196, 6.557225626610161], "label": "P", "properties": {}}, {"species": [{"element": "P", "occu": 1}], "abc": [0.01026027, 0.29728685, 0.16321507000000002], "xyz": [0.10880095988781001, 6.39494724081605, 6.5543816410160805], "label": "P", "properties": {}}, {"species": [{"element": "P", "occu": 1}], "abc": [0.01408431, 0.70148555, 0.27553497], "xyz": [0.14935147392393, 15.089678815073151, 11.06491789530168], "label": "P", "properties": {}}, {"species": [{"element": "P", "occu": 1}], "abc": [0.00730995, 0.99705968, 0.22255891], "xyz": [0.07751546272485, 21.44778367944944, 8.93750824448104], "label": "P", "properties": {}}, {"species": [{"element": "P", "occu": 1}], "abc": [0.51152291, 0.89529229, 0.3361154], "xyz": [5.4242416244997305, 19.25866199483557, 13.4977034107376], "label": "P", "properties": {}}, {"species": [{"element": "P", "occu": 1}], "abc": [0.01158969, 0.39525786, 0.33609753000000003], "xyz": [0.12289826649807, 8.50240486996938, 13.496985788278321], "label": "P", "properties": {}}, {"species": [{"element": "S", "occu": 1}], "abc": [0.6133538, 0.0633315, 0.06678592], "xyz": [6.5040668706414, 1.3623259864395, 2.68198523534848], "label": "S", "properties": {}}, {"species": [{"element": "S", "occu": 1}], "abc": [0.61407798, 0.37088605, 0.007636680000000007], "xyz": [6.51174614995194, 7.978142060789651, 0.3066733677859203], "label": "S", "properties": {}}, {"species": [{"element": "S", "occu": 1}], "abc": [0.61778581, 0.76625492, 0.12330193], "xyz": [6.5510643611784305, 16.48293487053236, 4.951552000031921], "label": "S", "properties": {}}, {"species": [{"element": "S", "occu": 1}], "abc": [0.62160035, 0.42494754, 0.08823058], "xyz": [6.59151413623605, 9.14106055620882, 3.54315869072752], "label": "S", "properties": {}}, {"species": [{"element": "S", "occu": 1}], "abc": [0.11785917, 0.2662438, 0.12322063000000003], "xyz": [1.2497907781745101, 5.727179167845399, 4.948287159184721], "label": "S", "properties": {}}, {"species": [{"element": "S", "occu": 1}], "abc": [0.11347661, 0.56326964, 0.06679293], "xyz": [1.20331766053083, 12.116511813938121, 2.68226674253592], "label": "S", "properties": {}}, {"species": [{"element": "S", "occu": 1}], "abc": [0.11410084, 0.87090124, 0.007608250000000004], "xyz": [1.20993705974652, 18.73398531338092, 0.30553167743800014], "label": "S", "properties": {}}, {"species": [{"element": "S", "occu": 1}], "abc": [0.12163343, 0.92496895, 0.08821066], "xyz": [1.28981341996329, 19.89703760742535, 3.54235874448304], "label": "S", "properties": {}}, {"species": [{"element": "S", "occu": 1}], "abc": [0.39529128, 0.16245699, 0.09450382000000002], "xyz": [4.19170944812184, 3.49461767297067, 3.7950791113460807], "label": "S", "properties": {}}, {"species": [{"element": "S", "occu": 1}], "abc": [0.40967563, 0.47607962, 0.03353247], "xyz": [4.34424257710989, 10.24096441644746, 1.34659505244168], "label": "S", "properties": {}}, {"species": [{"element": "S", "occu": 1}], "abc": [0.38526504, 0.32968371, 0.06198012000000001], "xyz": [4.085390166459121, 7.09183716537243, 2.4889941880732804], "label": "S", "properties": {}}, {"species": [{"element": "S", "occu": 1}], "abc": [0.40334014, 0.01835634, 0.12378524000000002], "xyz": [4.27706038859442, 0.39486383549922, 4.97096073594656], "label": "S", "properties": {}}, {"species": [{"element": "S", "occu": 1}], "abc": [0.89560825, 0.66252713, 0.09445600000000001], "xyz": [9.49712213064975, 14.25164295682529, 3.7931587584640005], "label": "S", "properties": {}}, {"species": [{"element": "S", "occu": 1}], "abc": [0.90969579, 0.97608308, 0.03352610000000001], "xyz": [9.64650785582637, 20.99655534462164, 1.3463392463384005], "label": "S", "properties": {}}, {"species": [{"element": "S", "occu": 1}], "abc": [0.90328394, 0.51842556, 0.12377731], "xyz": [9.57851593800582, 11.15186932920348, 4.9706422834506405], "label": "S", "properties": {}}, {"species": [{"element": "S", "occu": 1}], "abc": [0.88529467, 0.82969266, 0.06196506000000001], "xyz": [9.387755866031009, 17.84754618911778, 2.4883894094366403], "label": "S", "properties": {}}, {"species": [{"element": "S", "occu": 1}], "abc": [0.23948373, 0.05546248, 0.026568070000000006], "xyz": [2.53951013974419, 1.1930552375418402, 1.0669190672480802], "label": "S", "properties": {}}, {"species": [{"element": "S", "occu": 1}], "abc": [0.12113609, 0.25019283, 0.02087726], "xyz": [1.2845395753772701, 5.38190622249339, 0.8383878379534401], "label": "S", "properties": {}}, {"species": [{"element": "S", "occu": 1}], "abc": [0.25872621, 0.74472299, 0.07740853], "xyz": [2.7435593796396303, 16.019760813748672, 3.10856741286232], "label": "S", "properties": {}}, {"species": [{"element": "S", "occu": 1}], "abc": [0.75869382, 0.24470682, 0.07741159], "xyz": [8.04526741274346, 5.2638964803450605, 3.10869029617096], "label": "S", "properties": {}}, {"species": [{"element": "S", "occu": 1}], "abc": [0.73952385, 0.55544779, 0.026579210000000006], "xyz": [7.84198707635655, 11.94825574046707, 1.0673664267442402], "label": "S", "properties": {}}, {"species": [{"element": "S", "occu": 1}], "abc": [0.62116274, 0.7501834, 0.02089246], "xyz": [6.586873674722221, 16.1372198734522, 0.8389982387022401], "label": "S", "properties": {}}, {"species": [{"element": "S", "occu": 1}], "abc": [0.63387577, 0.17182612, 0.23865881], "xyz": [6.72168395428431, 3.69615733758196, 9.58404712708664], "label": "S", "properties": {}}, {"species": [{"element": "S", "occu": 1}], "abc": [0.60259156, 0.4685171, 0.18118812], "xyz": [6.38994296917068, 10.078286799164301, 7.27614237642528], "label": "S", "properties": {}}, {"species": [{"element": "S", "occu": 1}], "abc": [0.62229639, 0.87030661, 0.29608033], "xyz": [6.5988950160881705, 18.72119420782813, 11.88997731164152], "label": "S", "properties": {}}, {"species": [{"element": "S", "occu": 1}], "abc": [0.63673467, 0.12124579, 0.14499585], "xyz": [6.75200002435101, 2.6081221898010702, 5.8227352245324004], "label": "S", "properties": {}}, {"species": [{"element": "S", "occu": 1}], "abc": [0.61726339, 0.52528376, 0.26233479], "xyz": [6.54552456568917, 11.29939629572408, 10.53482580607176], "label": "S", "properties": {}}, {"species": [{"element": "S", "occu": 1}], "abc": [0.60782719, 0.82644526, 0.2038614], "xyz": [6.445462128960569, 17.77769126055358, 8.1866546849616], "label": "S", "properties": {}}, {"species": [{"element": "S", "occu": 1}], "abc": [0.12238305, 0.37027117, 0.29607103], "xyz": [1.29776246765415, 7.96491535681861, 11.889603842762321], "label": "S", "properties": {}}, {"species": [{"element": "S", "occu": 1}], "abc": [0.13377862, 0.67179734, 0.23869228000000003], "xyz": [1.4186022656778599, 14.45105475005222, 9.585391213472322], "label": "S", "properties": {}}, {"species": [{"element": "S", "occu": 1}], "abc": [0.10252415, 0.96849949, 0.18117193], "xyz": [1.08717664658745, 20.83342448987317, 7.2754922193119205], "label": "S", "properties": {}}, {"species": [{"element": "S", "occu": 1}], "abc": [0.10782635, 0.3262394, 0.20379861000000002], "xyz": [1.14340172151405, 7.017746499300201, 8.18413316765784], "label": "S", "properties": {}}, {"species": [{"element": "S", "occu": 1}], "abc": [0.13675892, 0.62125591, 0.14500421000000002], "xyz": [1.45020567384876, 13.363856381455031, 5.823070944944241], "label": "S", "properties": {}}, {"species": [{"element": "S", "occu": 1}], "abc": [0.11714781, 0.02528592, 0.26232087000000004], "xyz": [1.2422474434644302, 0.54392625955536, 10.534266807491282], "label": "S", "properties": {}}, {"species": [{"element": "S", "occu": 1}], "abc": [0.40324206, 0.2758588, 0.26046275], "xyz": [4.27602033817218, 5.934007750140401, 10.459648528586001], "label": "S", "properties": {}}, {"species": [{"element": "S", "occu": 1}], "abc": [0.38697239, 0.56944767, 0.20970391000000002], "xyz": [4.10349508171617, 12.24940762114311, 8.42127787436104], "label": "S", "properties": {}}, {"species": [{"element": "S", "occu": 1}], "abc": [0.3937315, 0.86939001, 0.14791077000000002], "xyz": [4.1751693803445, 18.70147719498033, 5.939792418656881], "label": "S", "properties": {}}, {"species": [{"element": "S", "occu": 1}], "abc": [0.39253719, 0.42364963, 0.23741587000000003], "xyz": [4.1625047940905695, 9.11314117136779, 9.534133212171282], "label": "S", "properties": {}}, {"species": [{"element": "S", "occu": 1}], "abc": [0.39384169, 0.72321629, 0.17672490000000002], "xyz": [4.176337846454071, 15.557129480327571, 7.096908637605601], "label": "S", "properties": {}}, {"species": [{"element": "S", "occu": 1}], "abc": [0.3939764, 0.13159428, 0.28970451], "xyz": [4.1777663251692, 2.8307288996912403, 11.633937489127442], "label": "S", "properties": {}}, {"species": [{"element": "S", "occu": 1}], "abc": [0.89374715, 0.3693295, 0.14789989], "xyz": [9.477386834556452, 7.9446590623735, 5.93935550022616], "label": "S", "properties": {}}, {"species": [{"element": "S", "occu": 1}], "abc": [0.9031891, 0.77582763, 0.26049893], "xyz": [9.577510244877299, 16.68885375124179, 10.46110144299992], "label": "S", "properties": {}}, {"species": [{"element": "S", "occu": 1}], "abc": [0.88689365, 0.06942737, 0.20969291], "xyz": [9.40471161464595, 1.49345444717321, 8.42083613697704], "label": "S", "properties": {}}, {"species": [{"element": "S", "occu": 1}], "abc": [0.89392168, 0.22302252, 0.17659482], "xyz": [9.47923756865304, 4.79744478746316, 7.091684892250081], "label": "S", "properties": {}}, {"species": [{"element": "S", "occu": 1}], "abc": [0.89390088, 0.63157018, 0.28972229], "xyz": [9.47901700331064, 13.58572698379594, 11.63465149737176], "label": "S", "properties": {}}, {"species": [{"element": "S", "occu": 1}], "abc": [0.89249874, 0.92364313, 0.23741269000000004], "xyz": [9.46414856633022, 19.86851784965329, 9.534005509909361], "label": "S", "properties": {}}, {"species": [{"element": "S", "occu": 1}], "abc": [0.22098103, 0.14808527, 0.19104517000000001], "xyz": [2.34330560316609, 3.18546712978391, 7.67198123833048], "label": "S", "properties": {}}, {"species": [{"element": "S", "occu": 1}], "abc": [0.23158477, 0.44451529, 0.13652149000000002], "xyz": [2.45574875431131, 9.56198307219457, 5.482422350216561], "label": "S", "properties": {}}, {"species": [{"element": "S", "occu": 1}], "abc": [0.23014875, 0.85017374, 0.24791783], "xyz": [2.44052105032125, 18.28811537687342, 9.95587033374152], "label": "S", "properties": {}}, {"species": [{"element": "S", "occu": 1}], "abc": [0.73026628, 0.35007562, 0.24788161000000003], "xyz": [7.743818850546841, 7.53048821431546, 9.954415813009842], "label": "S", "properties": {}}, {"species": [{"element": "S", "occu": 1}], "abc": [0.7210159, 0.64812767, 0.19110280000000002], "xyz": [7.645726868237701, 13.941895697583112, 7.674295540643201], "label": "S", "properties": {}}, {"species": [{"element": "S", "occu": 1}], "abc": [0.73159961, 0.94452137, 0.13649972000000002], "xyz": [7.757957619199829, 20.317630359275213, 5.481548111775681], "label": "S", "properties": {}}, {"species": [{"element": "S", "occu": 1}], "abc": [0.61383752, 0.23022995, 0.31690465], "xyz": [6.509196287344561, 4.95248405203835, 12.726239188039601], "label": "S", "properties": {}}, {"species": [{"element": "S", "occu": 1}], "abc": [0.611645, 0.92372629, 0.37680240000000004], "xyz": [6.485946579435, 19.87030670715757, 15.131609678265601], "label": "S", "properties": {}}, {"species": [{"element": "S", "occu": 1}], "abc": [0.11179864, 0.42365784, 0.37677978], "xyz": [1.18552429381992, 9.11331777694872, 15.130701305572321], "label": "S", "properties": {}}, {"species": [{"element": "S", "occu": 1}], "abc": [0.11384312, 0.7302131, 0.31692245], "xyz": [1.20720417032136, 15.7076380911323, 12.7269539994428], "label": "S", "properties": {}}, {"species": [{"element": "S", "occu": 1}], "abc": [0.38461424, 0.96487107, 0.32194569], "xyz": [4.07848901622672, 20.755373427515313, 12.92867699006136], "label": "S", "properties": {}}, {"species": [{"element": "S", "occu": 1}], "abc": [0.40957998, 0.81810396, 0.3502812], "xyz": [4.343228294657941, 17.59826128099068, 14.066572813852801], "label": "S", "properties": {}}, {"species": [{"element": "S", "occu": 1}], "abc": [0.8847611, 0.46486795, 0.32191878], "xyz": [9.3820978347933, 9.99978981309235, 12.927596339788321], "label": "S", "properties": {}}, {"species": [{"element": "S", "occu": 1}], "abc": [0.90957064, 0.31809562, 0.35026152], "xyz": [9.64518075233592, 6.842565378975461, 14.06578250551488], "label": "S", "properties": {}}, {"species": [{"element": "S", "occu": 1}], "abc": [0.23873963, 0.2396401, 0.35776033], "xyz": [2.53161962670189, 5.1549060992233, 14.366919297561521], "label": "S", "properties": {}}, {"species": [{"element": "S", "occu": 1}], "abc": [0.25733498, 0.54983989, 0.30721617], "xyz": [2.72880663342294, 11.82762401850637, 12.33716975075448], "label": "S", "properties": {}}, {"species": [{"element": "S", "occu": 1}], "abc": [0.11853061, 0.04569728, 0.36268921000000004], "xyz": [1.25691079709283, 0.98299569809024, 14.564852984584242], "label": "S", "properties": {}}, {"species": [{"element": "S", "occu": 1}], "abc": [0.61882321, 0.54569846, 0.36294431], "xyz": [6.56206505763063, 11.738537581109181, 14.57509727609864], "label": "S", "properties": {}}, {"species": [{"element": "S", "occu": 1}], "abc": [0.73881972, 0.73969154, 0.35774583], "xyz": [7.83452040931116, 15.911529126760822, 14.36633700737352], "label": "S", "properties": {}}, {"species": [{"element": "S", "occu": 1}], "abc": [0.75707266, 0.04989222, 0.30718741], "xyz": [8.028076465123979, 1.0732331908632602, 12.33601480828504], "label": "S", "properties": {}}, {"species": [{"element": "Cl", "occu": 1}], "abc": [0.95240961, 0.08732878, 0.10782212000000002], "xyz": [10.09944960262983, 1.87853226842974, 4.3299146569212805], "label": "Cl", "properties": {}}, {"species": [{"element": "Cl", "occu": 1}], "abc": [0.96775609, 0.39358747, 0.05738213000000001], "xyz": [10.26218525723727, 8.466473055556511, 2.3043483631407207], "label": "Cl", "properties": {}}, {"species": [{"element": "Cl", "occu": 1}], "abc": [0.02025624, 0.70191945, 0.009586890000000008], "xyz": [0.21479925535272, 15.09901245229185, 0.3849897917541603], "label": "Cl", "properties": {}}, {"species": [{"element": "Cl", "occu": 1}], "abc": [0.52015206, 0.20192084, 0.009653380000000003], "xyz": [5.51574601990218, 4.34352585262772, 0.3876598934507201], "label": "Cl", "properties": {}}, {"species": [{"element": "Cl", "occu": 1}], "abc": [0.45245204, 0.58737292, 0.10787917000000002], "xyz": [4.79784803472012, 12.63499826542636, 4.332205667626481], "label": "Cl", "properties": {}}, {"species": [{"element": "Cl", "occu": 1}], "abc": [0.46780719, 0.89358127, 0.05737339], "xyz": [4.96067562690057, 19.22185618715191, 2.3039973827101603], "label": "Cl", "properties": {}}, {"species": [{"element": "Cl", "occu": 1}], "abc": [0.94966815, 0.20963256, 0.27481593], "xyz": [10.07037887841945, 4.5094129160344805, 11.036042727247919], "label": "Cl", "properties": {}}, {"species": [{"element": "Cl", "occu": 1}], "abc": [0.92297036, 0.49829373, 0.21732566000000003], "xyz": [9.78727276338708, 10.71881286972309, 8.727351684043041], "label": "Cl", "properties": {}}, {"species": [{"element": "Cl", "occu": 1}], "abc": [0.92869109, 0.79756155, 0.16651570000000002], "xyz": [9.84793597354227, 17.15637282158115, 6.686928155720801], "label": "Cl", "properties": {}}, {"species": [{"element": "Cl", "occu": 1}], "abc": [0.42872162, 0.29754759, 0.16650362000000002], "xyz": [4.5462082168068605, 6.400556027560469, 6.6864430477572805], "label": "Cl", "properties": {}}, {"species": [{"element": "Cl", "occu": 1}], "abc": [0.44954862, 0.70967634, 0.27482475], "xyz": [4.76705986998786, 15.26587116905922, 11.036396920314], "label": "Cl", "properties": {}}, {"species": [{"element": "Cl", "occu": 1}], "abc": [0.42276819, 0.99834695, 0.21731676], "xyz": [4.4830774318835696, 21.47547418689935, 8.72699427834144], "label": "Cl", "properties": {}}, {"species": [{"element": "Cl", "occu": 1}], "abc": [0.01834787, 0.59291858, 0.37462638000000004], "xyz": [0.19456270331060999, 12.754291140693141, 15.044225188962722], "label": "Cl", "properties": {}}, {"species": [{"element": "Cl", "occu": 1}], "abc": [0.9666228, 0.89941498, 0.32805373], "xyz": [10.2501677333484, 19.34734531547434, 13.17396331833112], "label": "Cl", "properties": {}}, {"species": [{"element": "Cl", "occu": 1}], "abc": [0.46686756, 0.39954341, 0.32806042], "xyz": [4.95071169359868, 8.59459147744253, 13.17423197497648], "label": "Cl", "properties": {}}, {"species": [{"element": "Cl", "occu": 1}], "abc": [0.51820073, 0.09290852, 0.37462975000000004], "xyz": [5.49505391559519, 1.99855823970116, 15.044360521234001], "label": "Cl", "properties": {}}]}, "formula": "(Li3PS4)12.0(Li2S)18.0(LiCl)16.0", "bandgap": 1.8040000000000003, "slab_thickness": 15.41837835952848}